Workbook

Sheet TD
A2: Grupo Ramo2 | B2: Suma de Prima neta | C2: Suma de Comisión prima neta | D2: Suma de Comisión complementaria | E2: Suma de Comisión colaborador
A3: Autos | B3: 91830.96 | C3: 11457.53 | D3: 230.12 | E3: 33.54
A4: Flotas | B4: 2343138.7 | C4: 269823.97 | D4: 637 | E4: 2353.22
A5: Hogar | B5: 11331.92 | C5: 2812.44 | D5: 0 | E5: 0
A6: Ingeniería | B6: 10471.9 | C6: 1737.73 | D6: 339.74 | E6: 0
A7: Líneas Financieras | B7: 13408.47 | C7: 2725.6 | D7: 0 | E7: 0
A8: Náutica | B8: 44.88 | C8: 7.85 | D8: 0 | E8: 0
A9: Particulares Resto | B9: 4341.64 | C9: 1098.64 | D9: 0 | E9: 9.44
A10: Property | B10: 55367.36 | C10: 11810.86 | D10: 78.84 | E10: 56.91
A11: Responsabilidad Civil | B11: 68815.44 | C11: 13779.49 | D11: 198.16 | E11: 59.83
A12: Resto de lineas | B12: 19024.27 | C12: 1464.06 | D12: 0 | E12: 0
A13: Seguros Personales (No Vida) Colectivos | B13: 32195.11 | C13: 6329.09 | D13: 66.66 | E13: 48.69
A14: Seguros Personales (No Vida) Particular | B14: 79384.48 | C14: 7066.48 | D14: 12.91 | E14: 0
... A19: Total general | B19: 3220079.9 | C19: 432985.37 | D19: 2010.37 | E19: 2942.22
I22: mes | J22: 2
A23: M-1
A24: Grupo Ramo2 | B24: Suma de Prima neta | C24: Suma de Comisión prima neta | D24: Suma de Comisión complementaria | E24: Suma de Comisión colaborador | I24: Grupo Ramo2 | J24: Suma de Prima neta | K24: Suma de Comisión prima neta | L24: Suma de Comisión complementaria | M24: Suma de Comisión colaborador
A25: Autos | B25: 65616.9 | C25: 8185.05 | D25: 157.24 | E25: 5.5 | I25: Autos | J25: 25760.95 | K25: 3199.98 | L25: 30.52 | M25: 28.04
A26: Flotas | B26: 1970814.9 | C26: 226315.43 | D26: 466.8 | E26: 1067.87 | I26: Flotas | J26: 239219.58 | K26: 27513.28 | L26: 173.58 | M26: 740.76
A27: Hogar | B27: 12062.32 | C27: 3087.19 | D27: 0 | E27: 0 | I27: Hogar | J27: 1838.52 | K27: 367.53 | L27: 0 | M27: 0
A28: Ingeniería | B28: 3466.87 | C28: 662.94 | D28: 0 | E28: 0 | I28: Ingeniería | J28: 4828.03 | K28: 724.2 | L28: 254.68 | M28: 0
A29: Líneas Financieras | B29: 6863.92 | C29: 1330.67 | D29: 0 | E29: 0 | I29: Líneas Financieras | J29: 6544.55 | K29: 1394.93 | L29: 0 | M29: 0
A30: Particulares Resto | B30: 3006.94 | C30: 819.05 | D30: 0 | E30: 9.44 | I30: Náutica | J30: 44.88 | K30: 7.85 | L30: 0 | M30: 0
A31: Property | B31: 49479.94 | C31: 10486.8 | D31: 16.8 | E31: 56.91 | I31: Particulares Resto | J31: 1334.7 | K31: 263.63 | L31: 0 | M31: 0
A32: Responsabilidad Civil | B32: 53225.41 | C32: 10652.89 | D32: 0 | E32: 31.65 | I32: Property | J32: 6417.93 | K32: 1437.07 | L32: 14.64 | M32: 0
A33: Seguros Personales (No Vida) Colectivos | B33: 20726.07 | C33: 4181.97 | D33: 24.77 | E33: 31.88 | I33: Responsabilidad Civil | J33: 15590.03 | K33: 3126.6 | L33: 198.16 | M33: 28.18
A34: Seguros Personales (No Vida) Particular | B34: 45806.53 | C34: 4037.57 | D34: 12.91 | E34: 0 | I34: Resto de lineas | J34: 19024.27 | K34: 1464.06 | L34: 0 | M34: 0
A35: Transporte | B35: 471606.08 | C35: 99602.27 | D35: 292.86 | E35: 363.01 | I35: Seguros Personales (No Vida) Colectivos | J35: 11020.45 | K35: 2057.41 | L35: 29.92 | M35: 5.74
A36: Vida Ahorro Particular | B36: -92.92 | C36: 24.31 | D36: 0 | E36: 0 | I36: Seguros Personales (No Vida) Particular | J36: 33151.47 | K36: 2980.71 | L36: 0 | M36: 0
... A39: Total general | B39: 2707449.3 | C39: 370330.88 | D39: 1121.47 | E39: 1566.26 | I39: Vida Riesgo Particular | J39: 1375.58 | K39: 298.35 | L39: 0 | M39: 0
I40: Total general | J40: 376424.24 | K40: 46354.08 | L40: 705.49 | M40: 820.3
A49: Agro
A50: Resto de Lineas | B50: =IFERROR(VLOOKUP(A50,$A$3:$B$21,2,0),0)-IFERROR(VLOOKUP(A50,$A$24:$C$42,2,0),0) -> 19024.27 | C50: =IFERROR(VLOOKUP(A50,$A$3:$C$22,3,0),0)-IFERROR(VLOOKUP(A50,$A$24:$C$42,3,0),0) -> 1464.06
A51: Retirada | B51: =IFERROR(VLOOKUP(A51,$A$3:$B$21,2,0),0)-IFERROR(VLOOKUP(A51,$A$24:$C$42,2,0),0) -> 0 | C51: =IFERROR(VLOOKUP(A51,$A$3:$C$22,3,0),0)-IFERROR(VLOOKUP(A51,$A$24:$C$42,3,0),0) -> 0
A52: Vida Ganado | B52: =IFERROR(VLOOKUP(A52,$A$3:$B$21,2,0),0)-IFERROR(VLOOKUP(A52,$A$24:$C$42,2,0),0) -> 0 | C52: =IFERROR(VLOOKUP(A52,$A$3:$C$22,3,0),0)-IFERROR(VLOOKUP(A52,$A$24:$C$42,3,0),0) -> 0
A53: Generales | B53: =IFERROR(VLOOKUP(A53,$A$3:$B$21,2,0),0)-IFERROR(VLOOKUP(A53,$A$24:$C$42,2,0),0) -> 0 | C53: =IFERROR(VLOOKUP(A53,$A$3:$C$22,3,0),0)-IFERROR(VLOOKUP(A53,$A$24:$C$42,3,0),0) -> 0
A54: B2B2C | B54: =IFERROR(VLOOKUP(A54,$A$3:$B$21,2,0),0)-IFERROR(VLOOKUP(A54,$A$24:$C$42,2,0),0) -> 0 | C54: =IFERROR(VLOOKUP(A54,$A$3:$C$22,3,0),0)-IFERROR(VLOOKUP(A54,$A$24:$C$42,3,0),0) -> 0
A55: Arte | B55: =IFERROR(VLOOKUP(A55,$A$3:$B$21,2,0),0)-IFERROR(VLOOKUP(A55,$A$24:$C$42,2,0),0) -> 0 | C55: =IFERROR(VLOOKUP(A55,$A$3:$C$22,3,0),0)-IFERROR(VLOOKUP(A55,$A$24:$C$42,3,0),0) -> 0
A56: Caución | B56: =IFERROR(VLOOKUP(A56,$A$3:$B$21,2,0),0)-IFERROR(VLOOKUP(A56,$A$24:$C$42,2,0),0) -> 0 | C56: =IFERROR(VLOOKUP(A56,$A$3:$C$22,3,0),0)-IFERROR(VLOOKUP(A56,$A$24:$C$42,3,0),0) -> 0
A57: Crédito Nacional | B57: =IFERROR(VLOOKUP(A57,$A$3:$B$21,2,0),0)-IFERROR(VLOOKUP(A57,$A$24:$C$42,2,0),0) -> 0 | C57: =IFERROR(VLOOKUP(A57,$A$3:$C$22,3,0),0)-IFERROR(VLOOKUP(A57,$A$24:$C$42,3,0),0) -> 0
A58: Crédito Internacional | B58: =IFERROR(VLOOKUP(A58,$A$3:$B$21,2,0),0)-IFERROR(VLOOKUP(A58,$A$24:$C$42,2,0),0) -> 0 | C58: =IFERROR(VLOOKUP(A58,$A$3:$C$22,3,0),0)-IFERROR(VLOOKUP(A58,$A$24:$C$42,3,0),0) -> 0
A59: Inmobiliario | B59: =IFERROR(VLOOKUP(A59,$A$3:$B$21,2,0),0)-IFERROR(VLOOKUP(A59,$A$24:$C$42,2,0),0) -> 0 | C59: =IFERROR(VLOOKUP(A59,$A$3:$C$22,3,0),0)-IFERROR(VLOOKUP(A59,$A$24:$C$42,3,0),0) -> 0
A60: Eventos | B60: =IFERROR(VLOOKUP(A60,$A$3:$B$21,2,0),0)-IFERROR(VLOOKUP(A60,$A$24:$C$42,2,0),0) -> 0 | C60: =IFERROR(VLOOKUP(A60,$A$3:$C$22,3,0),0)-IFERROR(VLOOKUP(A60,$A$24:$C$42,3,0),0) -> 0
A61: Property | B61: =IFERROR(VLOOKUP(A61,$A$3:$B$21,2,0),0)-IFERROR(VLOOKUP(A61,$A$24:$C$42,2,0),0) -> 5887.42 | C61: =IFERROR(VLOOKUP(A61,$A$3:$C$22,3,0),0)-IFERROR(VLOOKUP(A61,$A$24:$C$42,3,0),0) -> 1324.06
... A76: Vida Riesgo Colectivo | B76: =IFERROR(VLOOKUP(A76,$A$3:$B$21,2,0),0)-IFERROR(VLOOKUP(A76,$A$24:$C$42,2,0),0) -> 0 | C76: =IFERROR(VLOOKUP(A76,$A$3:$C$22,3,0),0)-IFERROR(VLOOKUP(A76,$A$24:$C$42,3,0),0) -> 0
B78: =SUM(B50:B77) -> 512630.65 | C78: =SUM(C50:C77) -> 62654.49 | D78: =+D19-D39 -> 888.9 | E78: =(E19-E39)*-1 -> -1375.96
B80: =+B78+B39-B19 -> 0 | C80: =+C78+C39-C19 -> 0

Sheet Sheet1
A1: Num. recibo | B1: Código recibo compañia | C1: Núm. Póliza | D1: Fecha anulación | E1: Fecha facturación | F1: Fecha Efecto | G1: Cliente | H1: Producto | I1: Ramo | J1: Prima neta | K1: . | L1: Comisión correduría | M1: .. | N1: Comisión prima neta | O1: ... | P1: Comisión complementaria | Q1: .... | R1: 1º Colaborador | S1: Comisión colaborador | T1: ..... | U1: Tipo | V1: Situación | W1: Empresa | X1: Compañía | Y1: Grupo Ramo | Z1: Gestión | AA1: Cliente.Direccion.CP | AB1: Cliente.Direccion.Localidad | AC1: Poliza.Cliente.Entidad | AD1: NIF | AE1: Ramo 2 | AF1: Grupo Ramo | AG1: Compañía | AH1: mes
A2: 2026000002 | B2: 469628063-J | C2: GPDIA3000224 | D2: 46023 | E2: 46023 | F2: 46023 | G2: RENOVATIA ACTIVOS, S.L.U. | H2: HOGAR PLUS 2015 | I2: M.HOGAR | J2: 150.61 | K2: Eur. | L2: 37.65 | M2: Eur. | N2: 37.65 | O2: Eur. | P2: 0 | Q2: Eur. | S2: 0,00 | T2: Eur. | U2: Cartera | V2: Anulado_Cia | W2: BANASEG-SV | X2: OCCIDENT GCO, S.A.U. DE SEGUROS Y REASEGUROS | Y2: M.HOGAR | Z2: Correduría | AA2: 47012 | AB2: VALLADOLID VALLADOLID | AC2: Empresa | AD2: B-47567334 | AE2: =+VLOOKUP(H2,'Mapeo Ramos'!A:C,3,0) -> Hogar | AF2: =+VLOOKUP(AE2,'Mapeo Ramos'!C:D,2,0) -> Hogar | AG2: =+VLOOKUP(X2,'Mapeo Ramos'!I:J,2,0) -> OCCIDENT | AH2: =+MONTH(E2) -> 1
A3: 2026000004 | B3: 469653253-C | C3: 547654663 | D3: 46023 | E3: 46023 | F3: 46023 | G3: RENOVATIA ACTIVOS, S.L.U. | H3: HOGAR PLUS 2015 | I3: M.HOGAR | J3: 160.31 | K3: Eur. | L3: 40.08 | M3: Eur. | N3: 40.08 | O3: Eur. | P3: 0 | Q3: Eur. | S3: 0,00 | T3: Eur. | U3: Cartera | V3: Anulado_Cia | W3: BANASEG-SV | X3: OCCIDENT GCO, S.A.U. DE SEGUROS Y REASEGUROS | Y3: M.HOGAR | Z3: Correduría | AA3: 47012 | AB3: VALLADOLID VALLADOLID | AC3: Empresa | AD3: B-47567334 | AE3: =+VLOOKUP(H3,'Mapeo Ramos'!A:C,3,0) -> Hogar | AF3: =+VLOOKUP(AE3,'Mapeo Ramos'!C:D,2,0) -> Hogar | AG3: =+VLOOKUP(X3,'Mapeo Ramos'!I:J,2,0) -> OCCIDENT | AH3: =+MONTH(E3) -> 1
A4: 2026000007 | B4: 469653252-T | C4: 547654662 | D4: 46023 | E4: 46023 | F4: 46023 | G4: RENOVATIA ACTIVOS, S.L.U. | H4: HOGAR PLUS 2015 | I4: M.HOGAR | J4: 147.42 | K4: Eur. | L4: 36.85 | M4: Eur. | N4: 36.85 | O4: Eur. | P4: 0 | Q4: Eur. | S4: 0,00 | T4: Eur. | U4: Cartera | V4: Anulado_Cia | W4: BANASEG-SV | X4: OCCIDENT GCO, S.A.U. DE SEGUROS Y REASEGUROS | Y4: M.HOGAR | Z4: Correduría | AA4: 47012 | AB4: VALLADOLID VALLADOLID | AC4: Empresa | AD4: B-47567334 | AE4: =+VLOOKUP(H4,'Mapeo Ramos'!A:C,3,0) -> Hogar | AF4: =+VLOOKUP(AE4,'Mapeo Ramos'!C:D,2,0) -> Hogar | AG4: =+VLOOKUP(X4,'Mapeo Ramos'!I:J,2,0) -> OCCIDENT | AH4: =+MONTH(E4) -> 1
A5: 2026000006 | B5: 469653254-L | C5: 547654667 | D5: 46023 | E5: 46023 | F5: 46023 | G5: RENOVATIA ACTIVOS, S.L.U. | H5: HOGAR PLUS 2015 | I5: M.HOGAR | J5: 145.23 | K5: Eur. | L5: 36.31 | M5: Eur. | N5: 36.31 | O5: Eur. | P5: 0 | Q5: Eur. | S5: 0,00 | T5: Eur. | U5: Cartera | V5: Anulado_Cia | W5: BANASEG-SV | X5: OCCIDENT GCO, S.A.U. DE SEGUROS Y REASEGUROS | Y5: M.HOGAR | Z5: Correduría | AA5: 47012 | AB5: VALLADOLID VALLADOLID | AC5: Empresa | AD5: B-47567334 | AE5: =+VLOOKUP(H5,'Mapeo Ramos'!A:C,3,0) -> Hogar | AF5: =+VLOOKUP(AE5,'Mapeo Ramos'!C:D,2,0) -> Hogar | AG5: =+VLOOKUP(X5,'Mapeo Ramos'!I:J,2,0) -> OCCIDENT | AH5: =+MONTH(E5) -> 1
A6: 2026000011 | B6: 469691708-T | C6: 548382890 | D6: 46023 | E6: 46023 | F6: 46023 | G6: RENOVATIA ACTIVOS, S.L.U. | H6: HOGAR PLUS 2015 | I6: M.HOGAR | J6: 1337.64 | K6: Eur. | L6: 334.41 | M6: Eur. | N6: 334.41 | O6: Eur. | P6: 0 | Q6: Eur. | S6: 0,00 | T6: Eur. | U6: Cartera | V6: Anulado_Cia | W6: BANASEG-SV | X6: OCCIDENT GCO, S.A.U. DE SEGUROS Y REASEGUROS | Y6: M.HOGAR | Z6: Correduría | AA6: 47012 | AB6: VALLADOLID VALLADOLID | AC6: Empresa | AD6: B-47567334 | AE6: =+VLOOKUP(H6,'Mapeo Ramos'!A:C,3,0) -> Hogar | AF6: =+VLOOKUP(AE6,'Mapeo Ramos'!C:D,2,0) -> Hogar | AG6: =+VLOOKUP(X6,'Mapeo Ramos'!I:J,2,0) -> OCCIDENT | AH6: =+MONTH(E6) -> 1
A7: 2026000010 | B7: 469667701-M | C7: 547986242 | D7: 46023 | E7: 46023 | F7: 46023 | G7: INDAMAL, S.L. | H7: HOGAR PLUS 2015 | I7: M.HOGAR | J7: 235.35 | K7: Eur. | L7: 58.84 | M7: Eur. | N7: 58.84 | O7: Eur. | P7: 0 | Q7: Eur. | S7: 0,00 | T7: Eur. | U7: Cartera | V7: Anulado_Cia | W7: BANASEG-SV | X7: OCCIDENT GCO, S.A.U. DE SEGUROS Y REASEGUROS | Y7: M.HOGAR | Z7: Correduría | AA7: 47012 | AB7: VALLADOLID VALLADOLID | AC7: Empresa | AD7: B-47486089 | AE7: =+VLOOKUP(H7,'Mapeo Ramos'!A:C,3,0) -> Hogar | AF7: =+VLOOKUP(AE7,'Mapeo Ramos'!C:D,2,0) -> Hogar | AG7: =+VLOOKUP(X7,'Mapeo Ramos'!I:J,2,0) -> OCCIDENT | AH7: =+MONTH(E7) -> 1
A8: 2026000013 | B8: 469705493-N | C8: 548645048 | D8: 46023 | E8: 46023 | F8: 46023 | G8: RENOVATIA ACTIVOS, S.L.U. | H8: HOGAR PLUS 2015 | I8: M.HOGAR | J8: 196.18 | K8: Eur. | L8: 49.04 | M8: Eur. | N8: 49.04 | O8: Eur. | P8: 0 | Q8: Eur. | S8: 0,00 | T8: Eur. | U8: Cartera | V8: Anulado_Cia | W8: BANASEG-SV | X8: OCCIDENT GCO, S.A.U. DE SEGUROS Y REASEGUROS | Y8: M.HOGAR | Z8: Correduría | AA8: 47012 | AB8: VALLADOLID VALLADOLID | AC8: Empresa | AD8: B-47567334 | AE8: =+VLOOKUP(H8,'Mapeo Ramos'!A:C,3,0) -> Hogar | AF8: =+VLOOKUP(AE8,'Mapeo Ramos'!C:D,2,0) -> Hogar | AG8: =+VLOOKUP(X8,'Mapeo Ramos'!I:J,2,0) -> OCCIDENT | AH8: =+MONTH(E8) -> 1
A9: 2026000014 | B9: 469705350-V | C9: 548644573 | D9: 46023 | E9: 46023 | F9: 46023 | G9: RENOVATIA ACTIVOS, S.L.U. | H9: HOGAR PLUS 2015 | I9: M.HOGAR | J9: 196.18 | K9: Eur. | L9: 49.04 | M9: Eur. | N9: 49.04 | O9: Eur. | P9: 0 | Q9: Eur. | S9: 0,00 | T9: Eur. | U9: Cartera | V9: Anulado_Cia | W9: BANASEG-SV | X9: OCCIDENT GCO, S.A.U. DE SEGUROS Y REASEGUROS | Y9: M.HOGAR | Z9: Correduría | AA9: 47012 | AB9: VALLADOLID VALLADOLID | AC9: Empresa | AD9: B-47567334 | AE9: =+VLOOKUP(H9,'Mapeo Ramos'!A:C,3,0) -> Hogar | AF9: =+VLOOKUP(AE9,'Mapeo Ramos'!C:D,2,0) -> Hogar | AG9: =+VLOOKUP(X9,'Mapeo Ramos'!I:J,2,0) -> OCCIDENT | AH9: =+MONTH(E9) -> 1
A10: 2026000017 | B10: 470042572-K | C10: GPDIN2700070 | D10: 46023 | E10: 46023 | F10: 46023 | G10: RENOVATIA ACTIVOS, S.L.U. | H10: COMERCIO PLUS | I10: M.COMERCIO | J10: 318.5 | K10: Eur. | L10: 71.66 | M10: Eur. | N10: 71.66 | O10: Eur. | P10: 0 | Q10: Eur. | S10: 0,00 | T10: Eur. | U10: Cartera | V10: Anulado_Cia | W10: BANASEG-SV | X10: OCCIDENT GCO, S.A.U. DE SEGUROS Y REASEGUROS | Y10: M.COMERCIO | Z10: Correduría | AA10: 47012 | AB10: VALLADOLID VALLADOLID | AC10: Empresa | AD10: B-47567334 | AE10: =+VLOOKUP(H10,'Mapeo Ramos'!A:C,3,0) -> Multirriesgo Comercios | AF10: =+VLOOKUP(AE10,'Mapeo Ramos'!C:D,2,0) -> Property | AG10: =+VLOOKUP(X10,'Mapeo Ramos'!I:J,2,0) -> OCCIDENT | AH10: =+MONTH(E10) -> 1
A11: 2026000033 | B11: 470787435-E | C11: 548626952 | D11: 46023 | E11: 46023 | F11: 46025 | G11: CARRETILLAS MAYOR, S.A. | H11: TURISMOS | I11: AUTOS | J11: 544.72 | K11: Eur. | L11: 65.36 | M11: Eur. | N11: 65.36 | O11: Eur. | P11: 0 | Q11: Eur. | S11: 0,00 | T11: Eur. | U11: Cartera | V11: Anulado_Cia | W11: BANASEG-SV | X11: OCCIDENT GCO, S.A.U. DE SEGUROS Y REASEGUROS | Y11: AUTOS | Z11: Correduría | AA11: 47260 | AB11: CABEZON DE PISUERGA VALLADOLID | AC11: Empresa | AD11: A-47067509 | AE11: =+VLOOKUP(H11,'Mapeo Ramos'!A:C,3,0) -> Autos Cat. 1 | AF11: =+VLOOKUP(AE11,'Mapeo Ramos'!C:D,2,0) -> Autos | AG11: =+VLOOKUP(X11,'Mapeo Ramos'!I:J,2,0) -> OCCIDENT | AH11: =+MONTH(E11) -> 1
A12: 2026000034 | B12: 470787456-M | C12: 548626974 | D12: 46023 | E12: 46023 | F12: 46025 | G12: CARRETILLAS MAYOR, S.A. | H12: TURISMOS | I12: AUTOS | J12: 577.24 | K12: Eur. | L12: 69.26 | M12: Eur. | N12: 69.26 | O12: Eur. | P12: 0 | Q12: Eur. | S12: 0,00 | T12: Eur. | U12: Cartera | V12: Anulado_Cia | W12: BANASEG-SV | X12: OCCIDENT GCO, S.A.U. DE SEGUROS Y REASEGUROS | Y12: AUTOS | Z12: Correduría | AA12: 47260 | AB12: CABEZON DE PISUERGA VALLADOLID | AC12: Empresa | AD12: A-47067509 | AE12: =+VLOOKUP(H12,'Mapeo Ramos'!A:C,3,0) -> Autos Cat. 1 | AF12: =+VLOOKUP(AE12,'Mapeo Ramos'!C:D,2,0) -> Autos | AG12: =+VLOOKUP(X12,'Mapeo Ramos'!I:J,2,0) -> OCCIDENT | AH12: =+MONTH(E12) -> 1
A13: 2026000035 | B13: 470787464-G | C13: 548626983 | D13: 46023 | E13: 46023 | F13: 46025 | G13: CARRETILLAS MAYOR, S.A. | H13: TURISMOS | I13: AUTOS | J13: 597.46 | K13: Eur. | L13: 71.7 | M13: Eur. | N13: 71.7 | O13: Eur. | P13: 0 | Q13: Eur. | S13: 0,00 | T13: Eur. | U13: Cartera | V13: Anulado_Cia | W13: BANASEG-SV | X13: OCCIDENT GCO, S.A.U. DE SEGUROS Y REASEGUROS | Y13: AUTOS | Z13: Correduría | AA13: 47260 | AB13: CABEZON DE PISUERGA VALLADOLID | AC13: Empresa | AD13: A-47067509 | AE13: =+VLOOKUP(H13,'Mapeo Ramos'!A:C,3,0) -> Autos Cat. 1 | AF13: =+VLOOKUP(AE13,'Mapeo Ramos'!C:D,2,0) -> Autos | AG13: =+VLOOKUP(X13,'Mapeo Ramos'!I:J,2,0) -> OCCIDENT | AH13: =+MONTH(E13) -> 1
... A37: 2026000344 | B37: 7601075821 | C37: D9A620000033 | D37: 46023 | E37: 46023 | F37: 46023 | G37: LOGISTICA Y DISTRIBUCION BARROSO, S.L. | H37: HELVETIA SEMI REMOLQUES | I37: AUTOS | J37: 463.07 | K37: Eur. | L37: 64.84 | M37: Eur. | N37: 64.84 | O37: Eur. | P37: 0 | Q37: Eur. | S37: 0,00 | T37: Eur. | U37: Cartera | V37: Anulado_Cia | W37: BANASEG-SV | X37: HELVETIA | Y37: AUTOS | Z37: Correduría | AA37: 41770 | AB37: MONTELLANO SEVILLA | AC37: Empresa | AD37: B-90000282 | AE37: =+VLOOKUP(H37,'Mapeo Ramos'!A:C,3,0) -> Autos Cat. 2 | AF37: =+VLOOKUP(AE37,'Mapeo Ramos'!C:D,2,0) -> Flotas | AG37: =+VLOOKUP(X37,'Mapeo Ramos'!I:J,2,0) -> HELVETIA | AH37: =+MONTH(E37) -> 1
A38: 2026000346 | B38: 7601075822 | C38: D9A960000003 | D38: 46023 | E38: 46023 | F38: 46023 | G38: ANDRES SDAD COOP. | H38: HELVETIA FLOTAS | I38: AUTO FLOTA | J38: 139.21 | K38: Eur. | L38: 19.46 | M38: Eur. | N38: 19.46 | O38: Eur. | P38: 0 | Q38: Eur. | R38: ASETRA | S38: 3.48 | T38: Eur. | U38: Cartera | V38: Anulado_Cia | W38: BANASEG-SV | X38: HELVETIA | Y38: AUTOS | Z38: Correduría | AA38: 47350 | AB38: QUINTANILLA DE ONESIMO VALLADOLID | AC38: Empresa | AD38: F-47303029 | AE38: =+VLOOKUP(H38,'Mapeo Ramos'!A:C,3,0) -> Autos Flotas | AF38: =+VLOOKUP(AE38,'Mapeo Ramos'!C:D,2,0) -> Flotas | AG38: =+VLOOKUP(X38,'Mapeo Ramos'!I:J,2,0) -> HELVETIA | AH38: =+MONTH(E38) -> 1
A39: 2026000348 | B39: 7601075825 | C39: V4A960000011 | D39: 46023 | E39: 46023 | F39: 46023 | G39: HERMANOS ANDRES CALLEJA, S.L. | H39: HELVETIA FLOTAS | I39: AUTO FLOTA | J39: 5593.53 | K39: Eur. | L39: 783.08 | M39: Eur. | N39: 783.08 | O39: Eur. | P39: 0 | Q39: Eur. | R39: ASETRA | S39: 139.84 | T39: Eur. | U39: Cartera | V39: Anulado_Cia | W39: BANASEG-SV | X39: HELVETIA | Y39: AUTOS | Z39: Correduría | AA39: 47350 | AB39: QUINTANILLA DE ONESIMO VALLADOLID | AC39: Empresa | AD39: B-47358288 | AE39: =+VLOOKUP(H39,'Mapeo Ramos'!A:C,3,0) -> Autos Flotas | AF39: =+VLOOKUP(AE39,'Mapeo Ramos'!C:D,2,0) -> Flotas | AG39: =+VLOOKUP(X39,'Mapeo Ramos'!I:J,2,0) -> HELVETIA | AH39: =+MONTH(E39) -> 1
A40: 2026000359 | B40: 7601075836 | C40: D9H150004281 | D40: 46023 | E40: 46023 | F40: 46023 | G40: INDAMAL, S.L. | H40: HOGAR ELITE/VITAL/TOP | I40: M.HOGAR | J40: 289.16 | K40: Eur. | L40: 72.31 | M40: Eur. | N40: 72.31 | O40: Eur. | P40: 0 | Q40: Eur. | S40: 0,00 | T40: Eur. | U40: Cartera | V40: Anulado_Cia | W40: BANASEG-SV | X40: HELVETIA | Y40: M.HOGAR | Z40: Correduría | AA40: 47012 | AB40: VALLADOLID VALLADOLID | AC40: Empresa | AD40: B-47486089 | AE40: =+VLOOKUP(H40,'Mapeo Ramos'!A:C,3,0) -> Hogar | AF40: =+VLOOKUP(AE40,'Mapeo Ramos'!C:D,2,0) -> Hogar | AG40: =+VLOOKUP(X40,'Mapeo Ramos'!I:J,2,0) -> HELVETIA | AH40: =+MONTH(E40) -> 1
A41: 2026000360 | B41: 7601075838 | C41: D9H150005170 | D41: 46023 | E41: 46023 | F41: 46023 | G41: INDAMAL, S.L. | H41: HOGAR ELITE/VITAL/TOP | I41: M.HOGAR | J41: 153.64 | K41: Eur. | L41: 38.42 | M41: Eur. | N41: 38.42 | O41: Eur. | P41: 0 | Q41: Eur. | S41: 0,00 | T41: Eur. | U41: Cartera | V41: Anulado_Cia | W41: BANASEG-SV | X41: HELVETIA | Y41: M.HOGAR | Z41: Correduría | AA41: 47012 | AB41: VALLADOLID VALLADOLID | AC41: Empresa | AD41: B-47486089 | AE41: =+VLOOKUP(H41,'Mapeo Ramos'!A:C,3,0) -> Hogar | AF41: =+VLOOKUP(AE41,'Mapeo Ramos'!C:D,2,0) -> Hogar | AG41: =+VLOOKUP(X41,'Mapeo Ramos'!I:J,2,0) -> HELVETIA | AH41: =+MONTH(E41) -> 1
A42: 2026000362 | B42: 7601075837 | C42: D9H150004555 | D42: 46023 | E42: 46023 | F42: 46023 | G42: INDAMAL, S.L. | H42: HOGAR ELITE/VITAL/TOP | I42: M.HOGAR | J42: 206.98 | K42: Eur. | L42: 51.76 | M42: Eur. | N42: 51.76 | O42: Eur. | P42: 0 | Q42: Eur. | S42: 0,00 | T42: Eur. | U42: Cartera | V42: Anulado_Cia | W42: BANASEG-SV | X42: HELVETIA | Y42: M.HOGAR | Z42: Correduría | AA42: 47012 | AB42: VALLADOLID VALLADOLID | AC42: Empresa | AD42: B-47486089 | AE42: =+VLOOKUP(H42,'Mapeo Ramos'!A:C,3,0) -> Hogar | AF42: =+VLOOKUP(AE42,'Mapeo Ramos'!C:D,2,0) -> Hogar | AG42: =+VLOOKUP(X42,'Mapeo Ramos'!I:J,2,0) -> HELVETIA | AH42: =+MONTH(E42) -> 1
A43: 2026000375 | B43: 7601075852 | C43: K3T300000003 | D43: 46023 | E43: 46023 | F43: 46023 | G43: TTES. AVICOLAS MANSO, S.L. | H43: HELVETIA MULTIRRIESGO TRANSPORTISTA | I43: A.MAQUINARIA | J43: 1689.28 | K43: Eur. | L43: 304.07 | M43: Eur. | N43: 304.07 | O43: Eur. | P43: 0 | Q43: Eur. | R43: ASETRA 2024 | S43: 0 | T43: Eur. | U43: Cartera | V43: Anulado_Cia | W43: BANASEG-SV | X43: HELVETIA | Y43: A.MAQUINARIA | Z43: Correduría | AA43: 47008 | AB43: VALLADOLID VALLADOLID | AC43: Empresa | AD43: B-47333042 | AE43: =+VLOOKUP(H43,'Mapeo Ramos'!A:C,3,0) -> Transportes Mercancías | AF43: =+VLOOKUP(AE43,'Mapeo Ramos'!C:D,2,0) -> Transporte | AG43: =+VLOOKUP(X43,'Mapeo Ramos'!I:J,2,0) -> HELVETIA | AH43: =+MONTH(E43) -> 1
A44: 2026000414 | B44: 7601075890 | C44: K3T300000071 | D44: 46023 | E44: 46023 | F44: 46023 | G44: TTES. AVICOLAS MANSO, S.L. | H44: HELVETIA MULTIRRIESGO TRANSPORTISTA | I44: A.MAQUINARIA | J44: 31.47 | K44: Eur. | L44: 5.67 | M44: Eur. | N44: 5.67 | O44: Eur. | P44: 0 | Q44: Eur. | R44: ASETRA 2024 | S44: 0 | T44: Eur. | U44: Cartera | V44: Anulado_Cia | W44: BANASEG-SV | X44: HELVETIA | Y44: A.MAQUINARIA | Z44: Correduría | AA44: 47008 | AB44: VALLADOLID VALLADOLID | AC44: Empresa | AD44: B-47333042 | AE44: =+VLOOKUP(H44,'Mapeo Ramos'!A:C,3,0) -> Transportes Mercancías | AF44: =+VLOOKUP(AE44,'Mapeo Ramos'!C:D,2,0) -> Transporte | AG44: =+VLOOKUP(X44,'Mapeo Ramos'!I:J,2,0) -> HELVETIA | AH44: =+MONTH(E44) -> 1
A45: 2026000416 | B45: 7601075891 | C45: K3T300000072 | D45: 46023 | E45: 46023 | F45: 46023 | G45: TTES. AVICOLAS MANSO, S.L. | H45: HELVETIA MULTIRRIESGO TRANSPORTISTA | I45: A.MAQUINARIA | J45: 1616.81 | K45: Eur. | L45: 291.02 | M45: Eur. | N45: 291.02 | O45: Eur. | P45: 0 | Q45: Eur. | R45: ASETRA 2024 | S45: 0 | T45: Eur. | U45: Cartera | V45: Anulado_Cia | W45: BANASEG-SV | X45: HELVETIA | Y45: A.MAQUINARIA | Z45: Correduría | AA45: 47008 | AB45: VALLADOLID VALLADOLID | AC45: Empresa | AD45: B-47333042 | AE45: =+VLOOKUP(H45,'Mapeo Ramos'!A:C,3,0) -> Transportes Mercancías | AF45: =+VLOOKUP(AE45,'Mapeo Ramos'!C:D,2,0) -> Transporte | AG45: =+VLOOKUP(X45,'Mapeo Ramos'!I:J,2,0) -> HELVETIA | AH45: =+MONTH(E45) -> 1
A46: 2026001664 | B46: 580586455 | C46: 12070250-02535 | D46: 46023 | E46: 46023 | F46: 46023 | G46: D-CUATRO 2014 TRANSPORTES,S.L. , | H46: ALLIANZ AUTO V. 08 COLECTIVO | I46: AUTO FLOTA | J46: 432.97 | K46: Eur. | L46: 51.96 | M46: Eur. | N46: 51.96 | O46: Eur. | P46: 0 | Q46: Eur. | S46: 0,00 | T46: Eur. | U46: Cartera | V46: Anulado_Cia | W46: BANASEG-SV | X46: ALLIANZ | Y46: AUTOS | Z46: Correduría | AA46: 40260 | AB46: FUENTEPELAYO SEGOVIA | AC46: Empresa | AD46: B-40256240 | AE46: =+VLOOKUP(H46,'Mapeo Ramos'!A:C,3,0) -> Autos Flotas | AF46: =+VLOOKUP(AE46,'Mapeo Ramos'!C:D,2,0) -> Flotas | AG46: =+VLOOKUP(X46,'Mapeo Ramos'!I:J,2,0) -> ALLIANZ | AH46: =+MONTH(E46) -> 1
A47: 2026001756 | B47: 580586257 | C47: 12070250-02366 | D47: 46023 | E47: 46023 | F47: 46023 | G47: ALFREDO MATE FRAILE | H47: ALLIANZ AUTO V. 08 COLECTIVO | I47: AUTO FLOTA | J47: 605.8 | K47: Eur. | L47: 72.7 | M47: Eur. | N47: 72.7 | O47: Eur. | P47: 0 | Q47: Eur. | S47: 0,00 | T47: Eur. | U47: Cartera | V47: Anulado_Cia | W47: BANASEG-SV | X47: ALLIANZ | Y47: AUTOS | Z47: Correduría | AA47: 34004 | AB47: PALENCIA PALENCIA | AC47: Particular | AD47: 12729153-X | AE47: =+VLOOKUP(H47,'Mapeo Ramos'!A:C,3,0) -> Autos Flotas | AF47: =+VLOOKUP(AE47,'Mapeo Ramos'!C:D,2,0) -> Flotas | AG47: =+VLOOKUP(X47,'Mapeo Ramos'!I:J,2,0) -> ALLIANZ | AH47: =+MONTH(E47) -> 1
A48: 2026001787 | B48: 580586596 | C48: 12070250-02593 | D48: 46023 | E48: 46023 | F48: 46023 | G48: TEODORO MARTIN DIAZ | H48: ALLIANZ AUTO V. 08 COLECTIVO | I48: AUTO FLOTA | J48: 214.07 | K48: Eur. | L48: 25.69 | M48: Eur. | N48: 25.69 | O48: Eur. | P48: 0 | Q48: Eur. | S48: 0,00 | T48: Eur. | U48: Cartera | V48: Anulado_Cia | W48: BANASEG-SV | X48: ALLIANZ | Y48: AUTOS | Z48: Correduría | AA48: 28223 | AB48: POZUELO DE ALARCON MADRID | AC48: Particular | AD48: 02082290-P | AE48: =+VLOOKUP(H48,'Mapeo Ramos'!A:C,3,0) -> Autos Flotas | AF48: =+VLOOKUP(AE48,'Mapeo Ramos'!C:D,2,0) -> Flotas | AG48: =+VLOOKUP(X48,'Mapeo Ramos'!I:J,2,0) -> ALLIANZ | AH48: =+MONTH(E48) -> 1
A49: 2026001788 | B49: 580586604 | C49: 12070250-02595 | D49: 46023 | E49: 46023 | F49: 46023 | G49: FERNANDO ROBLES VALDIVIESO | H49: ALLIANZ AUTO V. 08 COLECTIVO | I49: AUTO FLOTA | J49: 566.1 | K49: Eur. | L49: 67.93 | M49: Eur. | N49: 67.93 | O49: Eur. | P49: 0 | Q49: Eur. | S49: 0,00 | T49: Eur. | U49: Cartera | V49: Anulado_Cia | W49: BANASEG-SV | X49: ALLIANZ | Y49: AUTOS | Z49: Correduría | AA49: 47010 | AB49: VALLADOLID VALLADOLID | AC49: Particular | AD49: 12212755-P | AE49: =+VLOOKUP(H49,'Mapeo Ramos'!A:C,3,0) -> Autos Flotas | AF49: =+VLOOKUP(AE49,'Mapeo Ramos'!C:D,2,0) -> Flotas | AG49: =+VLOOKUP(X49,'Mapeo Ramos'!I:J,2,0) -> ALLIANZ | AH49: =+MONTH(E49) -> 1
A50: 2026001809 | B50: 580586828 | C50: 12070250-02651 | D50: 46023 | E50: 46023 | F50: 46023 | G50: ELSA HERNANDEZ CHAMORRO | H50: ALLIANZ AUTO V. 08 COLECTIVO | I50: AUTO FLOTA | J50: 819.94 | K50: Eur. | L50: 98.39 | M50: Eur. | N50: 98.39 | O50: Eur. | P50: 0 | Q50: Eur. | S50: 0,00 | T50: Eur. | U50: Cartera | V50: Anulado_Cia | W50: BANASEG-SV | X50: ALLIANZ | Y50: AUTOS | Z50: Correduría | AA50: 47005 | AB50: VALLADOLID VALLADOLID | AC50: Particular | AD50: 09407321-E | AE50: =+VLOOKUP(H50,'Mapeo Ramos'!A:C,3,0) -> Autos Flotas | AF50: =+VLOOKUP(AE50,'Mapeo Ramos'!C:D,2,0) -> Flotas | AG50: =+VLOOKUP(X50,'Mapeo Ramos'!I:J,2,0) -> ALLIANZ | AH50: =+MONTH(E50) -> 1
A51: 2026001811 | B51: 580586836 | C51: 12070250-02655 | D51: 46023 | E51: 46023 | F51: 46023 | G51: CARGAS Y SERV. AVICOLAS CANARIAS, S.L. | H51: ALLIANZ AUTO TODO RIESGO V.08 COLECTIVO | I51: AUTO FLOTA | J51: 1235.76 | K51: Eur. | L51: 148.29 | M51: Eur. | N51: 148.29 | O51: Eur. | P51: 0 | Q51: Eur. | R51: ASETRA | S51: 30.89 | T51: Eur. | U51: Cartera | V51: Anulado_Cia | W51: BANASEG-SV | X51: ALLIANZ | Y51: AUTOS | Z51: Correduría | AA51: 47008 | AB51: VALLADOLID VALLADOLID | AC51: Empresa | AD51: B-76514017 | AE51: =+VLOOKUP(H51,'Mapeo Ramos'!A:C,3,0) -> Autos Flotas | AF51: =+VLOOKUP(AE51,'Mapeo Ramos'!C:D,2,0) -> Flotas | AG51: =+VLOOKUP(X51,'Mapeo Ramos'!I:J,2,0) -> ALLIANZ | AH51: =+MONTH(E51) -> 1
A52: 2026001812 | B52: 580586844 | C52: 12070250-02656 | D52: 46023 | E52: 46023 | F52: 46023 | G52: CARGAS Y SERV. AVICOLAS CANARIAS, S.L. | H52: ALLIANZ AUTO TODO RIESGO V.08 COLECTIVO | I52: AUTO FLOTA | J52: 1235.76 | K52: Eur. | L52: 148.29 | M52: Eur. | N52: 148.29 | O52: Eur. | P52: 0 | Q52: Eur. | R52: ASETRA | S52: 30.89 | T52: Eur. | U52: Cartera | V52: Anulado_Cia | W52: BANASEG-SV | X52: ALLIANZ | Y52: AUTOS | Z52: Correduría | AA52: 47008 | AB52: VALLADOLID VALLADOLID | AC52: Empresa | AD52: B-76514017 | AE52: =+VLOOKUP(H52,'Mapeo Ramos'!A:C,3,0) -> Autos Flotas | AF52: =+VLOOKUP(AE52,'Mapeo Ramos'!C:D,2,0) -> Flotas | AG52: =+VLOOKUP(X52,'Mapeo Ramos'!I:J,2,0) -> ALLIANZ | AH52: =+MONTH(E52) -> 1
A53: 2026001813 | B53: 580586851 | C53: 12070250-02657 | D53: 46023 | E53: 46023 | F53: 46023 | G53: CARGAS Y SERV. AVICOLAS CANARIAS, S.L. | H53: ALLIANZ AUTO TODO RIESGO V.08 COLECTIVO | I53: AUTO FLOTA | J53: 1235.76 | K53: Eur. | L53: 148.29 | M53: Eur. | N53: 148.29 | O53: Eur. | P53: 0 | Q53: Eur. | R53: ASETRA | S53: 30.89 | T53: Eur. | U53: Cartera | V53: Anulado_Cia | W53: BANASEG-SV | X53: ALLIANZ | Y53: AUTOS | Z53: Correduría | AA53: 47008 | AB53: VALLADOLID VALLADOLID | AC53: Empresa | AD53: B-76514017 | AE53: =+VLOOKUP(H53,'Mapeo Ramos'!A:C,3,0) -> Autos Flotas | AF53: =+VLOOKUP(AE53,'Mapeo Ramos'!C:D,2,0) -> Flotas | AG53: =+VLOOKUP(X53,'Mapeo Ramos'!I:J,2,0) -> ALLIANZ | AH53: =+MONTH(E53) -> 1
A54: 2026001815 | B54: 580586877 | C54: 12070250-02659 | D54: 46023 | E54: 46023 | F54: 46023 | G54: CARGAS Y SERV. AVICOLAS CANARIAS, S.L. | H54: ALLIANZ AUTO TODO RIESGO V.08 COLECTIVO | I54: AUTO FLOTA | J54: 1235.76 | K54: Eur. | L54: 148.29 | M54: Eur. | N54: 148.29 | O54: Eur. | P54: 0 | Q54: Eur. | R54: ASETRA | S54: 30.89 | T54: Eur. | U54: Cartera | V54: Anulado_Cia | W54: BANASEG-SV | X54: ALLIANZ | Y54: AUTOS | Z54: Correduría | AA54: 47008 | AB54: VALLADOLID VALLADOLID | AC54: Empresa | AD54: B-76514017 | AE54: =+VLOOKUP(H54,'Mapeo Ramos'!A:C,3,0) -> Autos Flotas | AF54: =+VLOOKUP(AE54,'Mapeo Ramos'!C:D,2,0) -> Flotas | AG54: =+VLOOKUP(X54,'Mapeo Ramos'!I:J,2,0) -> ALLIANZ | AH54: =+MONTH(E54) -> 1
A55: 2026000900 | B55: 580588550 | C55: 12372022-01249 | D55: 46023 | E55: 46023 | F55: 46023 | G55: ESHREF ALIEV DZHAVIDOV | H55: AUTOGRUP V.03 (VH.COM. 2ª CATEG.) | I55: AUTO FLOTA | J55: 400.86 | K55: Eur. | L55: 48.1 | M55: Eur. | N55: 48.1 | O55: Eur. | P55: 0 | Q55: Eur. | S55: 0,00 | T55: Eur. | U55: Cartera | V55: Anulado_Cia | W55: BANASEG-SV | X55: ALLIANZ | Y55: AUTOS | Z55: Correduría | AA55: 47151 | AB55: BOECILLO VALLADOLID | AC55: Particular | AD55: X5527367-F | AE55: =+VLOOKUP(H55,'Mapeo Ramos'!A:C,3,0) -> Autos Flotas | AF55: =+VLOOKUP(AE55,'Mapeo Ramos'!C:D,2,0) -> Flotas | AG55: =+VLOOKUP(X55,'Mapeo Ramos'!I:J,2,0) -> ALLIANZ | AH55: =+MONTH(E55) -> 1
A56: 2026000902 | B56: 580588600 | C56: 12372022-01263 | D56: 46023 | E56: 46023 | F56: 46023 | G56: PRISCO E HIJO S.L. , | H56: AUTOGRUP V.03 (VH.COM. 2ª CATEG.) | I56: AUTO FLOTA | J56: 400.86 | K56: Eur. | L56: 48.1 | M56: Eur. | N56: 48.1 | O56: Eur. | P56: 0 | Q56: Eur. | R56: ASETRA | S56: 10.02 | T56: Eur. | U56: Cartera | V56: Anulado_Cia | W56: BANASEG-SV | X56: ALLIANZ | Y56: AUTOS | Z56: Correduría | AA56: 47013 | AB56: VALLADOLID VALLADOLID | AC56: Empresa | AD56: B-47787197 | AE56: =+VLOOKUP(H56,'Mapeo Ramos'!A:C,3,0) -> Autos Flotas | AF56: =+VLOOKUP(AE56,'Mapeo Ramos'!C:D,2,0) -> Flotas | AG56: =+VLOOKUP(X56,'Mapeo Ramos'!I:J,2,0) -> ALLIANZ | AH56: =+MONTH(E56) -> 1
A57: 2026000944 | B57: 580589038 | C57: 12372022-01455 | D57: 46023 | E57: 46023 | F57: 46023 | G57: PRISCO E HIJO S.L. , | H57: AUTOGRUP V.03 (VH.COM. 2ª CATEG.) | I57: AUTO FLOTA | J57: 947.12 | K57: Eur. | L57: 113.65 | M57: Eur. | N57: 113.65 | O57: Eur. | P57: 0 | Q57: Eur. | R57: ASETRA | S57: 23.68 | T57: Eur. | U57: Cartera | V57: Anulado_Cia | W57: BANASEG-SV | X57: ALLIANZ | Y57: AUTOS | Z57: Correduría | AA57: 47013 | AB57: VALLADOLID VALLADOLID | AC57: Empresa | AD57: B-47787197 | AE57: =+VLOOKUP(H57,'Mapeo Ramos'!A:C,3,0) -> Autos Flotas | AF57: =+VLOOKUP(AE57,'Mapeo Ramos'!C:D,2,0) -> Flotas | AG57: =+VLOOKUP(X57,'Mapeo Ramos'!I:J,2,0) -> ALLIANZ | AH57: =+MONTH(E57) -> 1
A58: 2026000950 | B58: 580589103 | C58: 12372022-01476 | D58: 46023 | E58: 46023 | F58: 46023 | G58: PRISCO E HIJO S.L. , | H58: AUTOGRUP V.03 (VH.COM. 2ª CATEG.) | I58: AUTO FLOTA | J58: 991.05 | K58: Eur. | L58: 118.93 | M58: Eur. | N58: 118.93 | O58: Eur. | P58: 0 | Q58: Eur. | R58: ASETRA | S58: 24.78 | T58: Eur. | U58: Cartera | V58: Anulado_Cia | W58: BANASEG-SV | X58: ALLIANZ | Y58: AUTOS | Z58: Correduría | AA58: 47013 | AB58: VALLADOLID VALLADOLID | AC58: Empresa | AD58: B-47787197 | AE58: =+VLOOKUP(H58,'Mapeo Ramos'!A:C,3,0) -> Autos Flotas | AF58: =+VLOOKUP(AE58,'Mapeo Ramos'!C:D,2,0) -> Flotas | AG58: =+VLOOKUP(X58,'Mapeo Ramos'!I:J,2,0) -> ALLIANZ | AH58: =+MONTH(E58) -> 1
A59: 2026000965 | B59: 580589236 | C59: 12372022-01534 | D59: 46023 | E59: 46023 | F59: 46023 | G59: PRISCO E HIJO S.L. , | H59: AUTOGRUP V.03 (VH.COM. 2ª CATEG.) | I59: AUTO FLOTA | J59: 2979.91 | K59: Eur. | L59: 357.59 | M59: Eur. | N59: 357.59 | O59: Eur. | P59: 0 | Q59: Eur. | R59: ASETRA | S59: 74.5 | T59: Eur. | U59: Cartera | V59: Anulado_Cia | W59: BANASEG-SV | X59: ALLIANZ | Y59: AUTOS | Z59: Correduría | AA59: 47013 | AB59: VALLADOLID VALLADOLID | AC59: Empresa | AD59: B-47787197 | AE59: =+VLOOKUP(H59,'Mapeo Ramos'!A:C,3,0) -> Autos Flotas | AF59: =+VLOOKUP(AE59,'Mapeo Ramos'!C:D,2,0) -> Flotas | AG59: =+VLOOKUP(X59,'Mapeo Ramos'!I:J,2,0) -> ALLIANZ | AH59: =+MONTH(E59) -> 1
A60: 2026000853 | B60: 580589384 | C60: 12372022-01555 | D60: 46023 | E60: 46023 | F60: 46023 | G60: PIENSOS A GRANEL ANDRES,SL. , | H60: AUTOGRUP V.03 (VH.COM. 2ª CATEG.) | I60: AUTO FLOTA | J60: 2693.12 | K60: Eur. | L60: 323.17 | M60: Eur. | N60: 323.17 | O60: Eur. | P60: 0 | Q60: Eur. | R60: ASETRA | S60: 67.33 | T60: Eur. | U60: Cartera | V60: Anulado_Cia | W60: BANASEG-SV | X60: ALLIANZ | Y60: AUTOS | Z60: Correduría | AA60: 47193 | AB60: CISTERNIGA VALLADOLID | AC60: Empresa | AD60: B-47754494 | AE60: =+VLOOKUP(H60,'Mapeo Ramos'!A:C,3,0) -> Autos Flotas | AF60: =+VLOOKUP(AE60,'Mapeo Ramos'!C:D,2,0) -> Flotas | AG60: =+VLOOKUP(X60,'Mapeo Ramos'!I:J,2,0) -> ALLIANZ | AH60: =+MONTH(E60) -> 1
A61: 2026000979 | B61: 580589392 | C61: 12372022-01557 | D61: 46023 | E61: 46023 | F61: 46023 | G61: PRISCO E HIJO S.L. , | H61: AUTOGRUP V.03 (VH.COM. 2ª CATEG.) | I61: AUTO FLOTA | J61: 400.86 | K61: Eur. | L61: 48.1 | M61: Eur. | N61: 48.1 | O61: Eur. | P61: 0 | Q61: Eur. | R61: ASETRA | S61: 10.02 | T61: Eur. | U61: Cartera | V61: Anulado_Cia | W61: BANASEG-SV | X61: ALLIANZ | Y61: AUTOS | Z61: Correduría | AA61: 47013 | AB61: VALLADOLID VALLADOLID | AC61: Empresa | AD61: B-47787197 | AE61: =+VLOOKUP(H61,'Mapeo Ramos'!A:C,3,0) -> Autos Flotas | AF61: =+VLOOKUP(AE61,'Mapeo Ramos'!C:D,2,0) -> Flotas | AG61: =+VLOOKUP(X61,'Mapeo Ramos'!I:J,2,0) -> ALLIANZ | AH61: =+MONTH(E61) -> 1
A62: 2026000993 | B62: 580589533 | C62: 12372022-01585 | D62: 46023 | E62: 46023 | F62: 46023 | G62: TTES. SABAS VALLADOLID, S.L. | H62: AUTOGRUP V.03 (VH.COM. 2ª CATEG.) | I62: AUTO FLOTA | J62: 1259.09 | K62: Eur. | L62: 151.09 | M62: Eur. | N62: 151.09 | O62: Eur. | P62: 0 | Q62: Eur. | S62: 0,00 | T62: Eur. | U62: Cartera | V62: Anulado_Cia | W62: BANASEG-SV | X62: ALLIANZ | Y62: AUTOS | Z62: Correduría | AA62: 47151 | AB62: BOECILLO VALLADOLID | AC62: Empresa | AD62: B-47634407 | AE62: =+VLOOKUP(H62,'Mapeo Ramos'!A:C,3,0) -> Autos Flotas | AF62: =+VLOOKUP(AE62,'Mapeo Ramos'!C:D,2,0) -> Flotas | AG62: =+VLOOKUP(X62,'Mapeo Ramos'!I:J,2,0) -> ALLIANZ | AH62: =+MONTH(E62) -> 1
A63: 2026000996 | B63: 580589574 | C63: 12372022-01593 | D63: 46023 | E63: 46023 | F63: 46023 | G63: JOSE MARIA DEL CAÑO MONEDERO | H63: AUTOGRUP V.03 (VH.COM. 2ª CATEG.) | I63: AUTO FLOTA | J63: 1259.09 | K63: Eur. | L63: 151.09 | M63: Eur. | N63: 151.09 | O63: Eur. | P63: 0 | Q63: Eur. | S63: 0,00 | T63: Eur. | U63: Cartera | V63: Anulado_Cia | W63: BANASEG-SV | X63: ALLIANZ | Y63: AUTOS | Z63: Correduría | AA63: 40219 | AB63: VILLAVERDE DE ISCAR SEGOVIA | AC63: Particular | AD63: 03452175-J | AE63: =+VLOOKUP(H63,'Mapeo Ramos'!A:C,3,0) -> Autos Flotas | AF63: =+VLOOKUP(AE63,'Mapeo Ramos'!C:D,2,0) -> Flotas | AG63: =+VLOOKUP(X63,'Mapeo Ramos'!I:J,2,0) -> ALLIANZ | AH63: =+MONTH(E63) -> 1
A64: 2026001019 | B64: 580589806 | C64: 12372022-01641 | D64: 46023 | E64: 46023 | F64: 46023 | G64: PRISCO E HIJO S.L. , | H64: AUTOGRUP V.03 (VH.COM. 2ª CATEG.) | I64: AUTO FLOTA | J64: 400.86 | K64: Eur. | L64: 48.1 | M64: Eur. | N64: 48.1 | O64: Eur. | P64: 0 | Q64: Eur. | R64: ASETRA | S64: 10.02 | T64: Eur. | U64: Cartera | V64: Anulado_Cia | W64: BANASEG-SV | X64: ALLIANZ | Y64: AUTOS | Z64: Correduría | AA64: 47013 | AB64: VALLADOLID VALLADOLID | AC64: Empresa | AD64: B-47787197 | AE64: =+VLOOKUP(H64,'Mapeo Ramos'!A:C,3,0) -> Autos Flotas | AF64: =+VLOOKUP(AE64,'Mapeo Ramos'!C:D,2,0) -> Flotas | AG64: =+VLOOKUP(X64,'Mapeo Ramos'!I:J,2,0) -> ALLIANZ | AH64: =+MONTH(E64) -> 1
A65: 2026001035 | B65: 580589962 | C65: 12372022-01671 | D65: 46023 | E65: 46023 | F65: 46023 | G65: PRISCO E HIJO S.L. , | H65: AUTOGRUP V.03 (VH.COM. 2ª CATEG.) | I65: AUTO FLOTA | J65: 400.86 | K65: Eur. | L65: 48.1 | M65: Eur. | N65: 48.1 | O65: Eur. | P65: 0 | Q65: Eur. | R65: ASETRA | S65: 10.02 | T65: Eur. | U65: Cartera | V65: Anulado_Cia | W65: BANASEG-SV | X65: ALLIANZ | Y65: AUTOS | Z65: Correduría | AA65: 47013 | AB65: VALLADOLID VALLADOLID | AC65: Empresa | AD65: B-47787197 | AE65: =+VLOOKUP(H65,'Mapeo Ramos'!A:C,3,0) -> Autos Flotas | AF65: =+VLOOKUP(AE65,'Mapeo Ramos'!C:D,2,0) -> Flotas | AG65: =+VLOOKUP(X65,'Mapeo Ramos'!I:J,2,0) -> ALLIANZ | AH65: =+MONTH(E65) -> 1
A66: 2026001064 | B66: 580590259 | C66: 12372022-01726 | D66: 46023 | E66: 46023 | F66: 46023 | G66: PIENSOS A GRANEL ANDRES,SL. , | H66: AUTOGRUP V.03 (VH.COM. 2ª CATEG.) | I66: AUTO FLOTA | J66: 1259.09 | K66: Eur. | L66: 151.09 | M66: Eur. | N66: 151.09 | O66: Eur. | P66: 0 | Q66: Eur. | R66: ASETRA 2024 | S66: 0 | T66: Eur. | U66: Cartera | V66: Anulado_Cia | W66: BANASEG-SV | X66: ALLIANZ | Y66: AUTOS | Z66: Correduría | AA66: 47193 | AB66: CISTERNIGA VALLADOLID | AC66: Empresa | AD66: B-47754494 | AE66: =+VLOOKUP(H66,'Mapeo Ramos'!A:C,3,0) -> Autos Flotas | AF66: =+VLOOKUP(AE66,'Mapeo Ramos'!C:D,2,0) -> Flotas | AG66: =+VLOOKUP(X66,'Mapeo Ramos'!I:J,2,0) -> ALLIANZ | AH66: =+MONTH(E66) -> 1
A67: 2026001070 | B67: 580590317 | C67: 12372022-01735 | D67: 46023 | E67: 46023 | F67: 46023 | G67: PRISCO E HIJO S.L. , | H67: AUTOGRUP V.03 (VH.COM. 2ª CATEG.) | I67: AUTO FLOTA | J67: 1211.94 | K67: Eur. | L67: 145.43 | M67: Eur. | N67: 145.43 | O67: Eur. | P67: 0 | Q67: Eur. | R67: ASETRA 2024 | S67: 0 | T67: Eur. | U67: Cartera | V67: Anulado_Cia | W67: BANASEG-SV | X67: ALLIANZ | Y67: AUTOS | Z67: Correduría | AA67: 47013 | AB67: VALLADOLID VALLADOLID | AC67: Empresa | AD67: B-47787197 | AE67: =+VLOOKUP(H67,'Mapeo Ramos'!A:C,3,0) -> Autos Flotas | AF67: =+VLOOKUP(AE67,'Mapeo Ramos'!C:D,2,0) -> Flotas | AG67: =+VLOOKUP(X67,'Mapeo Ramos'!I:J,2,0) -> ALLIANZ | AH67: =+MONTH(E67) -> 1
A68: 2026001094 | B68: 580590556 | C68: 12372022-01772 | D68: 46023 | E68: 46023 | F68: 46023 | G68: JUAN MANUEL DIEZ DIEZ | H68: AUTOGRUP V.03 (VH.COM. 2ª CATEG.) | I68: AUTO FLOTA | J68: 400.86 | K68: Eur. | L68: 48.1 | M68: Eur. | N68: 48.1 | O68: Eur. | P68: 0 | Q68: Eur. | R68: ASETRA 2024 | S68: 0 | T68: Eur. | U68: Cartera | V68: Anulado_Cia | W68: BANASEG-SV | X68: ALLIANZ | Y68: AUTOS | Z68: Correduría | AA68: 47250 | AB68: MOJADOS VALLADOLID | AC68: Particular | AD68: 09344956-X | AE68: =+VLOOKUP(H68,'Mapeo Ramos'!A:C,3,0) -> Autos Flotas | AF68: =+VLOOKUP(AE68,'Mapeo Ramos'!C:D,2,0) -> Flotas | AG68: =+VLOOKUP(X68,'Mapeo Ramos'!I:J,2,0) -> ALLIANZ | AH68: =+MONTH(E68) -> 1
A69: 2026001151 | B69: 580591133 | C69: 12372022-01846 | D69: 46023 | E69: 46023 | F69: 46023 | G69: ACEYE PRODUCTS S.L. | H69: AUTOGRUP V.03 (VH.COM. 2ª CATEG.) | I69: AUTO FLOTA | J69: 1710.99 | K69: Eur. | L69: 205.32 | M69: Eur. | N69: 205.32 | O69: Eur. | P69: 0 | Q69: Eur. | S69: 0,00 | T69: Eur. | U69: Cartera | V69: Anulado_Cia | W69: BANASEG-SV | X69: ALLIANZ | Y69: AUTOS | Z69: Correduría | AA69: 40200 | AB69: CUELLAR SEGOVIA | AC69: Empresa | AD69: B-40269086 | AE69: =+VLOOKUP(H69,'Mapeo Ramos'!A:C,3,0) -> Autos Flotas | AF69: =+VLOOKUP(AE69,'Mapeo Ramos'!C:D,2,0) -> Flotas | AG69: =+VLOOKUP(X69,'Mapeo Ramos'!I:J,2,0) -> ALLIANZ | AH69: =+MONTH(E69) -> 1
A70: 2026001164 | B70: 580591257 | C70: 12372022-01860 | D70: 46023 | E70: 46023 | F70: 46023 | G70: TRANSPORTES INTEGRALES GRIMATRANS, S.L. | H70: AUTOGRUP V.03 (VH.COM. 2ª CATEG.) | I70: AUTO FLOTA | J70: 320.52 | K70: Eur. | L70: 38.46 | M70: Eur. | N70: 38.46 | O70: Eur. | P70: 0 | Q70: Eur. | S70: 0,00 | T70: Eur. | U70: Cartera | V70: Anulado_Cia | W70: BANASEG-SV | X70: ALLIANZ | Y70: AUTOS | Z70: Correduría | AA70: 34192 | AB70: GRIJOTA PALENCIA | AC70: Empresa | AD70: B-05398136 | AE70: =+VLOOKUP(H70,'Mapeo Ramos'!A:C,3,0) -> Autos Flotas | AF70: =+VLOOKUP(AE70,'Mapeo Ramos'!C:D,2,0) -> Flotas | AG70: =+VLOOKUP(X70,'Mapeo Ramos'!I:J,2,0) -> ALLIANZ | AH70: =+MONTH(E70) -> 1
A71: 2026001184 | B71: 580591463 | C71: 12372022-01885 | D71: 46023 | E71: 46023 | F71: 46023 | G71: TRANSCAMINO TTES. ESPECIALES, S.L. | H71: AUTOGRUP V.03 (VH.COM. 2ª CATEG.) | I71: AUTO FLOTA | J71: 3639.58 | K71: Eur. | L71: 436.75 | M71: Eur. | N71: 436.75 | O71: Eur. | P71: 0 | Q71: Eur. | S71: 0,00 | T71: Eur. | U71: Cartera | V71: Anulado_Cia | W71: BANASEG-SV | X71: ALLIANZ | Y71: AUTOS | Z71: Correduría | AA71: 47162 | AB71: P.I. EL BRIZO - ALDEAMAYOR DE SAN MARTIN VALLADOLID | AC71: Empresa | AD71: B-47322094 | AE71: =+VLOOKUP(H71,'Mapeo Ramos'!A:C,3,0) -> Autos Flotas | AF71: =+VLOOKUP(AE71,'Mapeo Ramos'!C:D,2,0) -> Flotas | AG71: =+VLOOKUP(X71,'Mapeo Ramos'!I:J,2,0) -> ALLIANZ | AH71: =+MONTH(E71) -> 1
A72: 2026001201 | B72: 580591653 | C72: 12372022-01905 | D72: 46023 | E72: 46023 | F72: 46023 | G72: OSCAR VALENCIA MADRIGAL | H72: AUTOGRUP V.03 (VH.COM. 2ª CATEG.) | I72: AUTO FLOTA | J72: 1259.09 | K72: Eur. | L72: 151.09 | M72: Eur. | N72: 151.09 | O72: Eur. | P72: 0 | Q72: Eur. | S72: 0,00 | T72: Eur. | U72: Cartera | V72: Anulado_Cia | W72: BANASEG-SV | X72: ALLIANZ | Y72: AUTOS | Z72: Correduría | AA72: 45210 | AB72: YUNCOS TOLEDO | AC72: Particular | AD72: 52953297-Y | AE72: =+VLOOKUP(H72,'Mapeo Ramos'!A:C,3,0) -> Autos Flotas | AF72: =+VLOOKUP(AE72,'Mapeo Ramos'!C:D,2,0) -> Flotas | AG72: =+VLOOKUP(X72,'Mapeo Ramos'!I:J,2,0) -> ALLIANZ | AH72: =+MONTH(E72) -> 1
A73: 2026001210 | B73: 580591729 | C73: 12372022-01913 | D73: 46023 | E73: 46023 | F73: 46023 | G73: GERALA TRANS, S.L. | H73: AUTOGRUP V.03 (VH.COM. 2ª CATEG.) | I73: AUTO FLOTA | J73: 1679.43 | K73: Eur. | L73: 201.53 | M73: Eur. | N73: 201.53 | O73: Eur. | P73: 0 | Q73: Eur. | S73: 0,00 | T73: Eur. | U73: Cartera | V73: Anulado_Cia | W73: BANASEG-SV | X73: ALLIANZ | Y73: AUTOS | Z73: Correduría | AA73: 47260 | AB73: CABEZON DE PISUERGA VALLADOLID | AC73: Empresa | AD73: B-47758966 | AE73: =+VLOOKUP(H73,'Mapeo Ramos'!A:C,3,0) -> Autos Flotas | AF73: =+VLOOKUP(AE73,'Mapeo Ramos'!C:D,2,0) -> Flotas | AG73: =+VLOOKUP(X73,'Mapeo Ramos'!I:J,2,0) -> ALLIANZ | AH73: =+MONTH(E73) -> 1
A74: 2026001212 | B74: 580591745 | C74: 12372022-01915 | D74: 46023 | E74: 46023 | F74: 46023 | G74: ACEYE PRODUCTS S.L. | H74: AUTOGRUP V.03 (VH.COM. 2ª CATEG.) | I74: AUTO FLOTA | J74: 1606.65 | K74: Eur. | L74: 192.8 | M74: Eur. | N74: 192.8 | O74: Eur. | P74: 0 | Q74: Eur. | S74: 0,00 | T74: Eur. | U74: Cartera | V74: Anulado_Cia | W74: BANASEG-SV | X74: ALLIANZ | Y74: AUTOS | Z74: Correduría | AA74: 40200 | AB74: CUELLAR SEGOVIA | AC74: Empresa | AD74: B-40269086 | AE74: =+VLOOKUP(H74,'Mapeo Ramos'!A:C,3,0) -> Autos Flotas | AF74: =+VLOOKUP(AE74,'Mapeo Ramos'!C:D,2,0) -> Flotas | AG74: =+VLOOKUP(X74,'Mapeo Ramos'!I:J,2,0) -> ALLIANZ | AH74: =+MONTH(E74) -> 1
A75: 2026001220 | B75: 580591836 | C75: 12372022-01924 | D75: 46023 | E75: 46023 | F75: 46023 | G75: AKSINIYA TSANKOVA ASENOVA | H75: AUTOGRUP V.03 (VH.COM. 2ª CATEG.) | I75: AUTO FLOTA | J75: 1259.25 | K75: Eur. | L75: 151.11 | M75: Eur. | N75: 151.11 | O75: Eur. | P75: 0 | Q75: Eur. | S75: 0,00 | T75: Eur. | U75: Cartera | V75: Anulado_Cia | W75: BANASEG-SV | X75: ALLIANZ | Y75: AUTOS | Z75: Correduría | AA75: 47270 | AB75: CIGALES VALLADOLID | AC75: Particular | AD75: X3813740-H | AE75: =+VLOOKUP(H75,'Mapeo Ramos'!A:C,3,0) -> Autos Flotas | AF75: =+VLOOKUP(AE75,'Mapeo Ramos'!C:D,2,0) -> Flotas | AG75: =+VLOOKUP(X75,'Mapeo Ramos'!I:J,2,0) -> ALLIANZ | AH75: =+MONTH(E75) -> 1
A76: 2026001243 | B76: 580592065 | C76: 12372022-01947 | D76: 46023 | E76: 46023 | F76: 46023 | G76: SANCHEZ MORCILLO TTES, S.L. | H76: AUTOGRUP V.03 (VH.COM. 2ª CATEG.) | I76: AUTO FLOTA | J76: 1259.09 | K76: Eur. | L76: 151.09 | M76: Eur. | N76: 151.09 | O76: Eur. | P76: 0 | Q76: Eur. | S76: 0,00 | T76: Eur. | U76: Cartera | V76: Anulado_Cia | W76: BANASEG-SV | X76: ALLIANZ | Y76: AUTOS | Z76: Correduría | AA76: 02005 | AB76: ALBACETE ALBACETE | AC76: Empresa | AD76: B-02290377 | AE76: =+VLOOKUP(H76,'Mapeo Ramos'!A:C,3,0) -> Autos Flotas | AF76: =+VLOOKUP(AE76,'Mapeo Ramos'!C:D,2,0) -> Flotas | AG76: =+VLOOKUP(X76,'Mapeo Ramos'!I:J,2,0) -> ALLIANZ | AH76: =+MONTH(E76) -> 1
A77: 2026001357 | B77: 580596637 | C77: 12716155-01432 | D77: 46023 | E77: 46023 | F77: 46023 | G77: ASOC FAMILIARES ALZHEIMER VALL , | H77: AUTOGRUP V.03 (VH.COM 1ªCATEG.) | I77: AUTO FLOTA | J77: 1595.08 | K77: Eur. | L77: 191.41 | M77: Eur. | N77: 191.41 | O77: Eur. | P77: 0 | Q77: Eur. | S77: 0,00 | T77: Eur. | U77: Cartera | V77: Anulado_Cia | W77: BANASEG-SV | X77: ALLIANZ | Y77: AUTOS | Z77: Correduría | AA77: 47011 | AB77: VALLADOLID VALLADOLID | AC77: Empresa | AD77: G-47356290 | AE77: =+VLOOKUP(H77,'Mapeo Ramos'!A:C,3,0) -> Autos Flotas | AF77: =+VLOOKUP(AE77,'Mapeo Ramos'!C:D,2,0) -> Flotas | AG77: =+VLOOKUP(X77,'Mapeo Ramos'!I:J,2,0) -> ALLIANZ | AH77: =+MONTH(E77) -> 1
A78: 2026001364 | B78: 580596702 | C78: 12716155-01681 | D78: 46023 | E78: 46023 | F78: 46023 | G78: ZOE EL RAYO S.L. , | H78: AUTOGRUP V.03 (VH.COM. 2ª CATEG.) | I78: AUTO FLOTA | J78: 437.4 | K78: Eur. | L78: 52.49 | M78: Eur. | N78: 52.49 | O78: Eur. | P78: 0 | Q78: Eur. | S78: 0,00 | T78: Eur. | U78: Cartera | V78: Anulado_Cia | W78: BANASEG-SV | X78: ALLIANZ | Y78: AUTOS | Z78: Correduría | AA78: 47812 | AB78: PALAZUELO DE VEDIJA VALLADOLID | AC78: Empresa | AD78: B-47655964 | AE78: =+VLOOKUP(H78,'Mapeo Ramos'!A:C,3,0) -> Autos Flotas | AF78: =+VLOOKUP(AE78,'Mapeo Ramos'!C:D,2,0) -> Flotas | AG78: =+VLOOKUP(X78,'Mapeo Ramos'!I:J,2,0) -> ALLIANZ | AH78: =+MONTH(E78) -> 1
A79: 2026001375 | B79: 580596827 | C79: 12716155-01861 | D79: 46023 | E79: 46023 | F79: 46023 | G79: SUMINISTROS SEHICA S.L. , | H79: AUTOGRUP V.03 (VH.COM 1ªCATEG.) | I79: AUTO FLOTA | J79: 728.67 | K79: Eur. | L79: 87.44 | M79: Eur. | N79: 87.44 | O79: Eur. | P79: 0 | Q79: Eur. | S79: 0,00 | T79: Eur. | U79: Cartera | V79: Anulado_Cia | W79: BANASEG-SV | X79: ALLIANZ | Y79: AUTOS | Z79: Correduría | AA79: 47012 | AB79: VALLADOLID VALLADOLID | AC79: Empresa | AD79: B-37359148 | AE79: =+VLOOKUP(H79,'Mapeo Ramos'!A:C,3,0) -> Autos Flotas | AF79: =+VLOOKUP(AE79,'Mapeo Ramos'!C:D,2,0) -> Flotas | AG79: =+VLOOKUP(X79,'Mapeo Ramos'!I:J,2,0) -> ALLIANZ | AH79: =+MONTH(E79) -> 1
A80: 2026001379 | B80: 580596884 | C80: 12716155-01970 | D80: 46023 | E80: 46023 | F80: 46023 | G80: ZOE EL RAYO S.L. , | H80: AUTOGRUP V.03 (VH.COM. 2ª CATEG.) | I80: AUTO FLOTA | J80: 3735.27 | K80: Eur. | L80: 448.23 | M80: Eur. | N80: 448.23 | O80: Eur. | P80: 0 | Q80: Eur. | S80: 0,00 | T80: Eur. | U80: Cartera | V80: Anulado_Cia | W80: BANASEG-SV | X80: ALLIANZ | Y80: AUTOS | Z80: Correduría | AA80: 47812 | AB80: PALAZUELO DE VEDIJA VALLADOLID | AC80: Empresa | AD80: B-47655964 | AE80: =+VLOOKUP(H80,'Mapeo Ramos'!A:C,3,0) -> Autos Flotas | AF80: =+VLOOKUP(AE80,'Mapeo Ramos'!C:D,2,0) -> Flotas | AG80: =+VLOOKUP(X80,'Mapeo Ramos'!I:J,2,0) -> ALLIANZ | AH80: =+MONTH(E80) -> 1
... A117: 2026003757 | B117: 879887838 | C117: 12372022-02004 | D117: 46023 | E117: 46023 | F117: 46023 | G117: TRANSMISABE, S.L. | H117: AUTOGRUP V.03 (VH.COM. 2ª CATEG.) | I117: AUTO FLOTA | J117: 1259.09 | K117: Eur. | L117: 151.09 | M117: Eur. | N117: 151.09 | O117: Eur. | P117: 0 | Q117: Eur. | S117: 0,00 | T117: Eur. | U117: Producción | V117: Anulado | W117: BANASEG-SV | X117: ALLIANZ | Y117: AUTOS | Z117: Correduría | AA117: 41720 | AB117: LOS PALACIOS Y VILLAFRANCA SEVILLA | AC117: Empresa | AD117: B-90273434 | AE117: =+VLOOKUP(H117,'Mapeo Ramos'!A:C,3,0) -> Autos Flotas | AF117: =+VLOOKUP(AE117,'Mapeo Ramos'!C:D,2,0) -> Flotas | AG117: =+VLOOKUP(X117,'Mapeo Ramos'!I:J,2,0) -> ALLIANZ | AH117: =+MONTH(E117) -> 1
A118: 2026000507 | B118: 567316694 | C118: 23004346 | D118: 46024 | E118: 46024 | F118: 46023 | G118: MARIA DEL PILAR GRAÑEDA RAMOS | H118: ALLIANZ VH.COM. V03 (2ª CATEG.) | I118: AUTOS | J118: 222.56 | K118: Eur. | L118: 24.48 | M118: Eur. | N118: 24.48 | O118: Eur. | P118: 0 | Q118: Eur. | R118: SANCHEZ-VALENCIA DIEZ, JUAN CARLOS 001 | S118: 0 | T118: Eur. | U118: Cartera | V118: Anulado_Cia | W118: BANASEG-SV | X118: ALLIANZ | Y118: AUTOS | Z118: Correduría | AA118: 47013 | AB118: VALLADOLID VALLADOLID | AC118: Particular | AD118: 12217801-V | AE118: =+VLOOKUP(H118,'Mapeo Ramos'!A:C,3,0) -> Autos Cat. 2 | AF118: =+VLOOKUP(AE118,'Mapeo Ramos'!C:D,2,0) -> Flotas | AG118: =+VLOOKUP(X118,'Mapeo Ramos'!I:J,2,0) -> ALLIANZ | AH118: =+MONTH(E118) -> 1
A119: 2026000510 | B119: 567674092 | C119: 49707936 | D119: 46024 | E119: 46024 | F119: 46023 | G119: JAVIER MARTIN IGLESIAS FIGUEROS | H119: ALLIANZ VH.COM. V03 (2ª CATEG.) | I119: AUTOS | J119: 357.44 | K119: Eur. | L119: 35.74 | M119: Eur. | N119: 35.74 | O119: Eur. | P119: 0 | Q119: Eur. | S119: 0,00 | T119: Eur. | U119: Cartera | V119: Anulado_Cia | W119: BANASEG-SV | X119: ALLIANZ | Y119: AUTOS | Z119: Compañía | AA119: 47014 | AB119: VALLADOLID VALLADOLID | AC119: Particular | AD119: 44904063-J | AE119: =+VLOOKUP(H119,'Mapeo Ramos'!A:C,3,0) -> Autos Cat. 2 | AF119: =+VLOOKUP(AE119,'Mapeo Ramos'!C:D,2,0) -> Flotas | AG119: =+VLOOKUP(X119,'Mapeo Ramos'!I:J,2,0) -> ALLIANZ | AH119: =+MONTH(E119) -> 1
A120: 2026000517 | B120: 568238061 | C120: 31954368 | D120: 46024 | E120: 46024 | F120: 46023 | G120: CENTRO LOGISTICO MESETA NORTE, S.L.U. | H120: MULT. EMPRESARIAL | I120: M. INDUSTRIAL | J120: 6343.49 | K120: Eur. | L120: 1268.7 | M120: Eur. | N120: 1268.7 | O120: Eur. | P120: 0 | Q120: Eur. | R120: SANCHEZ-VALENCIA DIEZ, JUAN CARLOS 001 | S120: 0 | T120: Eur. | U120: Cartera | V120: Anulado_Cia | W120: BANASEG-SV | X120: ALLIANZ | Y120: MULTIRRIESGOS INDUSTRIAL | Z120: Correduría | AA120: 47012 | AB120: VALLADOLID VALLADOLID | AC120: Empresa | AD120: B-47750252 | AE120: =+VLOOKUP(H120,'Mapeo Ramos'!A:C,3,0) -> Multirriesgo Industriales (PYME) | AF120: =+VLOOKUP(AE120,'Mapeo Ramos'!C:D,2,0) -> Property | AG120: =+VLOOKUP(X120,'Mapeo Ramos'!I:J,2,0) -> ALLIANZ | AH120: =+MONTH(E120) -> 1
A121: 2026000520 | B121: 568308583 | C121: 36281302 | D121: 46024 | E121: 46024 | F121: 46023 | G121: VELAZQUEZ ASISTENCIA S.L.U. | H121: ACCIDENTES CONVENIO PYME | I121: ACCIDENTES | J121: 577.13 | K121: Eur. | L121: 115.43 | M121: Eur. | N121: 115.43 | O121: Eur. | P121: 0 | Q121: Eur. | R121: SANCHEZ-VALENCIA DIEZ, JUAN CARLOS 001 | S121: 0 | T121: Eur. | U121: Cartera | V121: Anulado_Cia | W121: BANASEG-SV | X121: ALLIANZ | Y121: ACCIDENTES | Z121: Correduría | AA121: 47270 | AB121: CIGALES VALLADOLID | AC121: Empresa | AD121: B-47633755 | AE121: =+VLOOKUP(H121,'Mapeo Ramos'!A:C,3,0) -> Accidentes Convenio | AF121: =+VLOOKUP(AE121,'Mapeo Ramos'!C:D,2,0) -> Seguros Personales (No Vida) Colectivos | AG121: =+VLOOKUP(X121,'Mapeo Ramos'!I:J,2,0) -> ALLIANZ | AH121: =+MONTH(E121) -> 1
A122: 2026000525 | B122: 568374742 | C122: 40618627 | D122: 46024 | E122: 46024 | F122: 46023 | G122: INDAMAL, S.L. | H122: ALLIANZ COMERCIO | I122: M.COMERCIO | J122: 345.04 | K122: Eur. | L122: 69.01 | M122: Eur. | N122: 69.01 | O122: Eur. | P122: 0 | Q122: Eur. | S122: 0,00 | T122: Eur. | U122: Cartera | V122: Anulado_Cia | W122: BANASEG-SV | X122: ALLIANZ | Y122: M.COMERCIO | Z122: Correduría | AA122: 47012 | AB122: VALLADOLID VALLADOLID | AC122: Empresa | AD122: B-47486089 | AE122: =+VLOOKUP(H122,'Mapeo Ramos'!A:C,3,0) -> Multirriesgo Comercios | AF122: =+VLOOKUP(AE122,'Mapeo Ramos'!C:D,2,0) -> Property | AG122: =+VLOOKUP(X122,'Mapeo Ramos'!I:J,2,0) -> ALLIANZ | AH122: =+MONTH(E122) -> 1
A123: 2026000529 | B123: 568394443 | C123: 41023470 | D123: 46024 | E123: 46024 | F123: 46023 | G123: MAGA CAPITAL PARTNERS, S.L. | H123: ALLIANZ COMERCIO | I123: M.COMERCIO | J123: 253.9 | K123: Eur. | L123: 50.78 | M123: Eur. | N123: 50.78 | O123: Eur. | P123: 0 | Q123: Eur. | R123: SANCHEZ-VALENCIA DIEZ, JUAN CARLOS 001 | S123: 0 | T123: Eur. | U123: Cartera | V123: Anulado_Cia | W123: BANASEG-SV | X123: ALLIANZ | Y123: M.COMERCIO | Z123: Correduría | AA123: 47012 | AB123: VALLADOLID VALLADOLID | AC123: Empresa | AD123: B-47720503 | AE123: =+VLOOKUP(H123,'Mapeo Ramos'!A:C,3,0) -> Multirriesgo Comercios | AF123: =+VLOOKUP(AE123,'Mapeo Ramos'!C:D,2,0) -> Property | AG123: =+VLOOKUP(X123,'Mapeo Ramos'!I:J,2,0) -> ALLIANZ | AH123: =+MONTH(E123) -> 1
A124: 2026000532 | B124: 568428514 | C124: 42867087 | D124: 46024 | E124: 46024 | F124: 46023 | G124: ALEJANDRO PARRA GARCIA | H124: ACCIDENTES CONVENIO PYME | I124: ACCIDENTES | J124: 47.53 | K124: Eur. | L124: 9.51 | M124: Eur. | N124: 9.51 | O124: Eur. | P124: 0 | Q124: Eur. | R124: SANCHEZ-VALENCIA DIEZ, JUAN CARLOS 001 | S124: 0 | T124: Eur. | U124: Cartera | V124: Anulado | W124: BANASEG-SV | X124: ALLIANZ | Y124: ACCIDENTES | Z124: Correduría | AA124: 47610 | AB124: ZARATAN VALLADOLID | AC124: Particular | AD124: 12243663-G | AE124: =+VLOOKUP(H124,'Mapeo Ramos'!A:C,3,0) -> Accidentes Convenio | AF124: =+VLOOKUP(AE124,'Mapeo Ramos'!C:D,2,0) -> Seguros Personales (No Vida) Colectivos | AG124: =+VLOOKUP(X124,'Mapeo Ramos'!I:J,2,0) -> ALLIANZ | AH124: =+MONTH(E124) -> 1
A125: 2026000538 | B125: 568477594 | C125: 46520413 | D125: 46024 | E125: 46024 | F125: 46023 | G125: FUENTES DE CEA, S.L. , | H125: ACCIDENTES CONVENIO PYME | I125: ACCIDENTES | J125: 113.31 | K125: Eur. | L125: 22.66 | M125: Eur. | N125: 22.66 | O125: Eur. | P125: 0 | Q125: Eur. | S125: 0,00 | T125: Eur. | U125: Cartera | V125: Anulado_Cia | W125: BANASEG-SV | X125: ALLIANZ | Y125: ACCIDENTES | Z125: Correduría | AA125: 47012 | AB125: VALLADOLID VALLADOLID | AC125: Empresa | AD125: B-47737325 | AE125: =+VLOOKUP(H125,'Mapeo Ramos'!A:C,3,0) -> Accidentes Convenio | AF125: =+VLOOKUP(AE125,'Mapeo Ramos'!C:D,2,0) -> Seguros Personales (No Vida) Colectivos | AG125: =+VLOOKUP(X125,'Mapeo Ramos'!I:J,2,0) -> ALLIANZ | AH125: =+MONTH(E125) -> 1
A126: 2026000545 | B126: 568593614 | C126: 50081695 | D126: 46024 | E126: 46024 | F126: 46023 | G126: CENTRO LOGISTICO MESETA NORTE, S.L.U. | H126: ACCIDENTES CONVENIO PYME | I126: ACCIDENTES | J126: 368.98 | K126: Eur. | L126: 73.8 | M126: Eur. | N126: 73.8 | O126: Eur. | P126: 0 | Q126: Eur. | S126: 0,00 | T126: Eur. | U126: Cartera | V126: Anulado_Cia | W126: BANASEG-SV | X126: ALLIANZ | Y126: ACCIDENTES | Z126: Correduría | AA126: 47012 | AB126: VALLADOLID VALLADOLID | AC126: Empresa | AD126: B-47750252 | AE126: =+VLOOKUP(H126,'Mapeo Ramos'!A:C,3,0) -> Accidentes Convenio | AF126: =+VLOOKUP(AE126,'Mapeo Ramos'!C:D,2,0) -> Seguros Personales (No Vida) Colectivos | AG126: =+VLOOKUP(X126,'Mapeo Ramos'!I:J,2,0) -> ALLIANZ | AH126: =+MONTH(E126) -> 1
A127: 2026000050 | B127: 8729231444 | C127: 1001016521 | D127: 46024 | E127: 46023 | F127: 46023 | G127: ANTONIO JUAREZ GIRALDO | H127: SEGURO AUTOMOVILES | I127: AUTOS | J127: 552.06 | K127: Eur. | L127: 66.24 | M127: Eur. | N127: 66.24 | O127: Eur. | P127: 0 | Q127: Eur. | S127: 0,00 | T127: Eur. | U127: Cartera | V127: Anulado | W127: BANASEG-SV | X127: MAPFRE ESPAÑA, S.A. | Y127: AUTOS | Z127: Correduría | AA127: 47193 | AB127: LA CISTERNIGA VALLADOLID | AC127: Particular | AD127: 12229169-T | AE127: =+VLOOKUP(H127,'Mapeo Ramos'!A:C,3,0) -> Autos Cat. 1 | AF127: =+VLOOKUP(AE127,'Mapeo Ramos'!C:D,2,0) -> Autos | AG127: =+VLOOKUP(X127,'Mapeo Ramos'!I:J,2,0) -> MAPFRE | AH127: =+MONTH(E127) -> 1
A128: 2026000117 | B128: 8750678768 | C128: 621974721877 | D128: 46024 | E128: 46023 | F128: 46023 | G128: HIJOS DE OCTAVIO MAT Y SERV,S.L , | H128: TRANSPORTES DE MERCANCIAS | I128: TRANSPORTES | J128: 963.81 | K128: Eur. | L128: 216.86 | M128: Eur. | N128: 216.86 | O128: Eur. | P128: 0 | Q128: Eur. | R128: ASETRA | S128: 24.1 | T128: Eur. | U128: Cartera | V128: Anulado | W128: BANASEG-SV | X128: MAPFRE ESPAÑA, S.A. | Y128: TRANSPORTES | Z128: Correduría | AA128: 47331 | AB128: SANTIBAÑEZ DE VALCORBA VALLADOLID | AC128: Empresa | AD128: B-47384078 | AE128: =+VLOOKUP(H128,'Mapeo Ramos'!A:C,3,0) -> Transportes Mercancías | AF128: =+VLOOKUP(AE128,'Mapeo Ramos'!C:D,2,0) -> Transporte | AG128: =+VLOOKUP(X128,'Mapeo Ramos'!I:J,2,0) -> MAPFRE | AH128: =+MONTH(E128) -> 1
A129: 2026000123 | B129: 8750599197 | C129: 622174710302 | D129: 46024 | E129: 46023 | F129: 46047 | G129: MARIN COTARELO TRANSPORTES, S. , | H129: TRANSPORTES DE MERCANCIAS | I129: TRANSPORTES | J129: 2294.8 | K129: Eur. | L129: 516.33 | M129: Eur. | N129: 516.33 | O129: Eur. | P129: 0 | Q129: Eur. | R129: ASETRA | S129: 57.37 | T129: Eur. | U129: Cartera | V129: Anulado | W129: BANASEG-SV | X129: MAPFRE ESPAÑA, S.A. | Y129: TRANSPORTES | Z129: Correduría | AA129: 47005 | AB129: VALLADOLID VALLADOLID | AC129: Empresa | AD129: B-47550199 | AE129: =+VLOOKUP(H129,'Mapeo Ramos'!A:C,3,0) -> Transportes Mercancías | AF129: =+VLOOKUP(AE129,'Mapeo Ramos'!C:D,2,0) -> Transporte | AG129: =+VLOOKUP(X129,'Mapeo Ramos'!I:J,2,0) -> MAPFRE | AH129: =+MONTH(E129) -> 1
A130: 2026000140 | B130: 8724040591 | C130: 781980091852 | D130: 46024 | E130: 46023 | F130: 46023 | G130: RENOVATIA ACTIVOS, S.L.U. | H130: MULTIRRIESGO EMPRESARIAL | I130: M. INDUSTRIAL | J130: 305.41 | K130: Eur. | L130: 68.72 | M130: Eur. | N130: 68.72 | O130: Eur. | P130: 0 | Q130: Eur. | S130: 0,00 | T130: Eur. | U130: Cartera | V130: Anulado | W130: BANASEG-SV | X130: MAPFRE ESPAÑA, S.A. | Y130: MULTIRRIESGOS INDUSTRIAL | Z130: Correduría | AA130: 47012 | AB130: VALLADOLID VALLADOLID | AC130: Empresa | AD130: B-47567334 | AE130: =+VLOOKUP(H130,'Mapeo Ramos'!A:C,3,0) -> Multirriesgo Industriales (PYME) | AF130: =+VLOOKUP(AE130,'Mapeo Ramos'!C:D,2,0) -> Property | AG130: =+VLOOKUP(X130,'Mapeo Ramos'!I:J,2,0) -> MAPFRE | AH130: =+MONTH(E130) -> 1
A131: 2026000561 | B131: 578370300 | C131: 12070250-02554 | D131: 46024 | E131: 46024 | F131: 46023 | G131: AURORA QUINTANILLA RODRIGUEZ | H131: ALLIANZ AUTO V. 08 COLECTIVO | I131: AUTO FLOTA | J131: 426.83 | K131: Eur. | L131: 51.22 | M131: Eur. | N131: 51.22 | O131: Eur. | P131: 0 | Q131: Eur. | S131: 0,00 | T131: Eur. | U131: Cartera | V131: Anulado_Cia | W131: BANASEG-SV | X131: ALLIANZ | Y131: AUTOS | Z131: Correduría | AA131: 47014 | AB131: VALLADOLID VALLADOLID | AC131: Particular | AD131: 71132903-K | AE131: =+VLOOKUP(H131,'Mapeo Ramos'!A:C,3,0) -> Autos Flotas | AF131: =+VLOOKUP(AE131,'Mapeo Ramos'!C:D,2,0) -> Flotas | AG131: =+VLOOKUP(X131,'Mapeo Ramos'!I:J,2,0) -> ALLIANZ | AH131: =+MONTH(E131) -> 1
A132: 2026000582 | B132: 578370565 | C132: 12070250-02636 | D132: 46024 | E132: 46024 | F132: 46023 | G132: KARIM SAOULA LABLAQ | H132: ALLIANZ AUTO V. 08 COLECTIVO | I132: AUTO FLOTA | J132: 518.77 | K132: Eur. | L132: 62.25 | M132: Eur. | N132: 62.25 | O132: Eur. | P132: 0 | Q132: Eur. | S132: 0,00 | T132: Eur. | U132: Cartera | V132: Anulado_Cia | W132: BANASEG-SV | X132: ALLIANZ | Y132: AUTOS | Z132: Correduría | AA132: 47009 | AB132: LA OVERUELA VALLADOLID | AC132: Particular | AD132: 71328245-R | AE132: =+VLOOKUP(H132,'Mapeo Ramos'!A:C,3,0) -> Autos Flotas | AF132: =+VLOOKUP(AE132,'Mapeo Ramos'!C:D,2,0) -> Flotas | AG132: =+VLOOKUP(X132,'Mapeo Ramos'!I:J,2,0) -> ALLIANZ | AH132: =+MONTH(E132) -> 1
A133: 2026000562 | B133: 578383303 | C133: 12716155-02669 | D133: 46024 | E133: 46024 | F133: 46023 | G133: BCM CARGO EUROPE, S.L. | H133: AUTOGRUP V.03 (VH.COM. 2ª CATEG.) | I133: AUTO FLOTA | J133: 1894.87 | K133: Eur. | L133: 227.38 | M133: Eur. | N133: 227.38 | O133: Eur. | P133: 0 | Q133: Eur. | S133: 0,00 | T133: Eur. | U133: Cartera | V133: Anulado_Cia | W133: BANASEG-SV | X133: ALLIANZ | Y133: AUTOS | Z133: Correduría | AA133: 24413 | AB133: MOLINASECA LEON | AC133: Empresa | AD133: B-24657934 | AE133: =+VLOOKUP(H133,'Mapeo Ramos'!A:C,3,0) -> Autos Flotas | AF133: =+VLOOKUP(AE133,'Mapeo Ramos'!C:D,2,0) -> Flotas | AG133: =+VLOOKUP(X133,'Mapeo Ramos'!I:J,2,0) -> ALLIANZ | AH133: =+MONTH(E133) -> 1
A134: 2026000583 | B134: 578989588 | C134: 36780076-01309 | D134: 46024 | E134: 46024 | F134: 46023 | G134: LUCIANO SANCHEZ VEGA | H134: ALLIANZ AUTO TODO RIESGO V.08 COLECTIVO | I134: AUTO FLOTA | J134: 1204.14 | K134: Eur. | L134: 144.5 | M134: Eur. | N134: 144.5 | O134: Eur. | P134: 0 | Q134: Eur. | S134: 0,00 | T134: Eur. | U134: Cartera | V134: Anulado_Cia | W134: BANASEG-SV | X134: ALLIANZ | Y134: AUTOS | Z134: Correduría | AA134: 47009 | AB134: LA OVERUELA VALLADOLID | AC134: Particular | AD134: 13692568-R | AE134: =+VLOOKUP(H134,'Mapeo Ramos'!A:C,3,0) -> Autos Flotas | AF134: =+VLOOKUP(AE134,'Mapeo Ramos'!C:D,2,0) -> Flotas | AG134: =+VLOOKUP(X134,'Mapeo Ramos'!I:J,2,0) -> ALLIANZ | AH134: =+MONTH(E134) -> 1
A135: 2026000581 | B135: 578989679 | C135: 36780076-01320 | D135: 46024 | E135: 46024 | F135: 46023 | G135: JUAN CARLOS IBAÑEZ CRESPO | H135: AUTOGRUP V.03 (VH.COM. 2ª CATEG.) | I135: AUTO FLOTA | J135: 309.11 | K135: Eur. | L135: 37.09 | M135: Eur. | N135: 37.09 | O135: Eur. | P135: 0 | Q135: Eur. | S135: 0,00 | T135: Eur. | U135: Cartera | V135: Anulado_Cia | W135: BANASEG-SV | X135: ALLIANZ | Y135: AUTOS | Z135: Correduría | AA135: 47009 | AB135: VALLADOLID VALLADOLID | AC135: Particular | AD135: 17439338-W | AE135: =+VLOOKUP(H135,'Mapeo Ramos'!A:C,3,0) -> Autos Flotas | AF135: =+VLOOKUP(AE135,'Mapeo Ramos'!C:D,2,0) -> Flotas | AG135: =+VLOOKUP(X135,'Mapeo Ramos'!I:J,2,0) -> ALLIANZ | AH135: =+MONTH(E135) -> 1
A136: 2026000556 | B136: 578989737 | C136: 36780076-01330 | D136: 46024 | E136: 46024 | F136: 46023 | G136: ALEJANDRO GOMEZ GARCIA | H136: ALLIANZ AUTO V. 08 COLECTIVO | I136: AUTO FLOTA | J136: 470.19 | K136: Eur. | L136: 56.42 | M136: Eur. | N136: 56.42 | O136: Eur. | P136: 0 | Q136: Eur. | S136: 0,00 | T136: Eur. | U136: Cartera | V136: Anulado_Cia | W136: BANASEG-SV | X136: ALLIANZ | Y136: AUTOS | Z136: Correduría | AA136: 40197 | AB136: SAN CRISTOBAL DE SEGOVIA SEGOVIA | AC136: Particular | AD136: 03449122-L | AE136: =+VLOOKUP(H136,'Mapeo Ramos'!A:C,3,0) -> Autos Flotas | AF136: =+VLOOKUP(AE136,'Mapeo Ramos'!C:D,2,0) -> Flotas | AG136: =+VLOOKUP(X136,'Mapeo Ramos'!I:J,2,0) -> ALLIANZ | AH136: =+MONTH(E136) -> 1
A137: 2026000255 | B137: 8751156715 | C137: 1001016759 | D137: 46024 | E137: 46023 | F137: 46023 | G137: GESTION LOGISTICA DE CARGAS, S , | H137: SEGURO AUTOMOVILES | I137: AUTOS | J137: 367.81 | K137: Eur. | L137: 44.15 | M137: Eur. | N137: 44.15 | O137: Eur. | P137: 0 | Q137: Eur. | S137: 0,00 | T137: Eur. | U137: Cartera | V137: Anulado | W137: BANASEG-SV | X137: MAPFRE ESPAÑA, S.A. | Y137: AUTOS | Z137: Correduría | AA137: 47620 | AB137: VILLANUBLA VALLADOLID | AC137: Empresa | AD137: B-47092754 | AE137: =+VLOOKUP(H137,'Mapeo Ramos'!A:C,3,0) -> Autos Cat. 1 | AF137: =+VLOOKUP(AE137,'Mapeo Ramos'!C:D,2,0) -> Autos | AG137: =+VLOOKUP(X137,'Mapeo Ramos'!I:J,2,0) -> MAPFRE | AH137: =+MONTH(E137) -> 1
A138: 2026000327 | B138: 8724047724 | C138: 741880013327 | D138: 46024 | E138: 46023 | F138: 46023 | G138: INDAMAL, S.L. | H138: COMERCIOS Y OFICINAS | I138: M.COMERCIO | J138: 195.32 | K138: Eur. | L138: 43.95 | M138: Eur. | N138: 43.95 | O138: Eur. | P138: 0 | Q138: Eur. | S138: 0,00 | T138: Eur. | U138: Cartera | V138: Anulado | W138: BANASEG-SV | X138: MAPFRE ESPAÑA, S.A. | Y138: M.COMERCIO | Z138: Correduría | AA138: 47012 | AB138: VALLADOLID VALLADOLID | AC138: Empresa | AD138: B-47486089 | AE138: =+VLOOKUP(H138,'Mapeo Ramos'!A:C,3,0) -> Multirriesgo Comercios | AF138: =+VLOOKUP(AE138,'Mapeo Ramos'!C:D,2,0) -> Property | AG138: =+VLOOKUP(X138,'Mapeo Ramos'!I:J,2,0) -> MAPFRE | AH138: =+MONTH(E138) -> 1
A139: 2026000335 | B139: 7601045244 | C139: D9C300000079 | D139: 46024 | E139: 46023 | F139: 46023 | G139: HIJOS DE OCTAVIO MAT Y SERV,S.L , | H139: ACCIDENTES CONVENIO | I139: ACCIDENTES | J139: 51.46 | K139: Eur. | L139: 9.78 | M139: Eur. | N139: 9.78 | O139: Eur. | P139: 0 | Q139: Eur. | R139: ASETRA | S139: 1.29 | T139: Eur. | U139: Cartera | V139: Anulado_Cia | W139: BANASEG-SV | X139: HELVETIA | Y139: ACCIDENTES | Z139: Correduría | AA139: 47331 | AB139: SANTIBAÑEZ DE VALCORBA VALLADOLID | AC139: Empresa | AD139: B-47384078 | AE139: =+VLOOKUP(H139,'Mapeo Ramos'!A:C,3,0) -> Accidentes Convenio | AF139: =+VLOOKUP(AE139,'Mapeo Ramos'!C:D,2,0) -> Seguros Personales (No Vida) Colectivos | AG139: =+VLOOKUP(X139,'Mapeo Ramos'!I:J,2,0) -> HELVETIA | AH139: =+MONTH(E139) -> 1
A140: 2026000336 | B140: 7601045245 | C140: D9R180000610 | D140: 46024 | E140: 46023 | F140: 46046 | G140: HIJOS DE OCTAVIO MAT Y SERV,S.L , | H140: HELVETIA RESP. CIVIL | I140: R.C. | J140: 627.01 | K140: Eur. | L140: 141.08 | M140: Eur. | N140: 141.08 | O140: Eur. | P140: 0 | Q140: Eur. | R140: ASETRA | S140: 15.68 | T140: Eur. | U140: Cartera | V140: Anulado | W140: BANASEG-SV | X140: HELVETIA | Y140: R.C. | Z140: Correduría | AA140: 47331 | AB140: SANTIBAÑEZ DE VALCORBA VALLADOLID | AC140: Empresa | AD140: B-47384078 | AE140: =+VLOOKUP(H140,'Mapeo Ramos'!A:C,3,0) -> Responsabilidad Civil Empresa | AF140: =+VLOOKUP(AE140,'Mapeo Ramos'!C:D,2,0) -> Responsabilidad Civil | AG140: =+VLOOKUP(X140,'Mapeo Ramos'!I:J,2,0) -> HELVETIA | AH140: =+MONTH(E140) -> 1
A141: 2026000338 | B141: 7601045243 | C141: V4A960000020 | D141: 46024 | E141: 46023 | F141: 46023 | G141: HIJOS DE OCTAVIO MAT Y SERV,S.L , | H141: HELVETIA FLOTAS | I141: AUTO FLOTA | J141: 702.54 | K141: Eur. | L141: 98.33 | M141: Eur. | N141: 98.33 | O141: Eur. | P141: 0 | Q141: Eur. | R141: ASETRA | S141: 17.56 | T141: Eur. | U141: Cartera | V141: Anulado_Cia | W141: BANASEG-SV | X141: HELVETIA | Y141: AUTOS | Z141: Correduría | AA141: 47331 | AB141: SANTIBAÑEZ DE VALCORBA VALLADOLID | AC141: Empresa | AD141: B-47384078 | AE141: =+VLOOKUP(H141,'Mapeo Ramos'!A:C,3,0) -> Autos Flotas | AF141: =+VLOOKUP(AE141,'Mapeo Ramos'!C:D,2,0) -> Flotas | AG141: =+VLOOKUP(X141,'Mapeo Ramos'!I:J,2,0) -> HELVETIA | AH141: =+MONTH(E141) -> 1
A142: 2026000342 | B142: 7601075818 | C142: D9A220000043 | D142: 46024 | E142: 46023 | F142: 46023 | G142: JUAN JOSE MARIN LOPEZ | H142: HELVETIA CAMIONES | I142: AUTOS | J142: 1888.94 | K142: Eur. | L142: 264.46 | M142: Eur. | N142: 264.46 | O142: Eur. | P142: 0 | Q142: Eur. | S142: 0,00 | T142: Eur. | U142: Cartera | V142: Anulado_Cia | W142: BANASEG-SV | X142: HELVETIA | Y142: AUTOS | Z142: Correduría | AA142: 06800 | AB142: MERIDA BADAJOZ | AC142: Particular | AD142: 25608248-W | AE142: =+VLOOKUP(H142,'Mapeo Ramos'!A:C,3,0) -> Autos Cat. 2 | AF142: =+VLOOKUP(AE142,'Mapeo Ramos'!C:D,2,0) -> Flotas | AG142: =+VLOOKUP(X142,'Mapeo Ramos'!I:J,2,0) -> HELVETIA | AH142: =+MONTH(E142) -> 1
A143: 2026000343 | B143: 7601075819 | C143: D9A510000062 | D143: 46024 | E143: 46023 | F143: 46023 | G143: AGRICENTRO SALAMANCA, S.L. | H143: HELVETIA VEHICULOS INDUSTRIALES | I143: AUTOS | J143: 76.17 | K143: Eur. | L143: 10.66 | M143: Eur. | N143: 10.66 | O143: Eur. | P143: 0 | Q143: Eur. | S143: 0,00 | T143: Eur. | U143: Cartera | V143: Anulado_Cia | W143: BANASEG-SV | X143: HELVETIA | Y143: AUTOS | Z143: Correduría | AA143: 37008 | AB143: SALAMANCA SALAMANCA | AC143: Empresa | AD143: B-37366507 | AE143: =+VLOOKUP(H143,'Mapeo Ramos'!A:C,3,0) -> Autos Cat. 2 | AF143: =+VLOOKUP(AE143,'Mapeo Ramos'!C:D,2,0) -> Flotas | AG143: =+VLOOKUP(X143,'Mapeo Ramos'!I:J,2,0) -> HELVETIA | AH143: =+MONTH(E143) -> 1
A144: 2026000354 | B144: 7601075831 | C144: V4A960000025 | D144: 46024 | E144: 46023 | F144: 46023 | G144: GRACALSA,S.L. | H144: HELVETIA FLOTAS | I144: AUTO FLOTA | J144: 1066.91 | K144: Eur. | L144: 149.35 | M144: Eur. | N144: 149.35 | O144: Eur. | P144: 0 | Q144: Eur. | R144: ASETRA | S144: 26.67 | T144: Eur. | U144: Cartera | V144: Anulado_Cia | W144: BANASEG-SV | X144: HELVETIA | Y144: AUTOS | Z144: Correduría | AA144: 47350 | AB144: QUINTANILLA DE ONESIMO VALLADOLID | AC144: Empresa | AD144: B-47325956 | AE144: =+VLOOKUP(H144,'Mapeo Ramos'!A:C,3,0) -> Autos Flotas | AF144: =+VLOOKUP(AE144,'Mapeo Ramos'!C:D,2,0) -> Flotas | AG144: =+VLOOKUP(X144,'Mapeo Ramos'!I:J,2,0) -> HELVETIA | AH144: =+MONTH(E144) -> 1
A145: 2026000363 | B145: 7601075839 | C145: D9H150005172 | D145: 46024 | E145: 46023 | F145: 46023 | G145: INDAMAL, S.L. | H145: HOGAR ELITE/VITAL/TOP | I145: M.HOGAR | J145: 152.19 | K145: Eur. | L145: 38.05 | M145: Eur. | N145: 38.05 | O145: Eur. | P145: 0 | Q145: Eur. | S145: 0,00 | T145: Eur. | U145: Cartera | V145: Anulado_Cia | W145: BANASEG-SV | X145: HELVETIA | Y145: M.HOGAR | Z145: Correduría | AA145: 47012 | AB145: VALLADOLID VALLADOLID | AC145: Empresa | AD145: B-47486089 | AE145: =+VLOOKUP(H145,'Mapeo Ramos'!A:C,3,0) -> Hogar | AF145: =+VLOOKUP(AE145,'Mapeo Ramos'!C:D,2,0) -> Hogar | AG145: =+VLOOKUP(X145,'Mapeo Ramos'!I:J,2,0) -> HELVETIA | AH145: =+MONTH(E145) -> 1
A146: 2026000555 | B146: 581095522 | C146: 36780076-00986 | D146: 46024 | E146: 46024 | F146: 46023 | G146: ADOLFO REDONDO FRANCISCO | H146: ALLIANZ AUTO V. 08 COLECTIVO | I146: AUTO FLOTA | J146: 245.74 | K146: Eur. | L146: 29.49 | M146: Eur. | N146: 29.49 | O146: Eur. | P146: 0 | Q146: Eur. | S146: 0,00 | T146: Eur. | U146: Cartera | V146: Anulado_Cia | W146: BANASEG-SV | X146: ALLIANZ | Y146: AUTOS | Z146: Correduría | AA146: 47010 | AB146: VALLADOLID VALLADOLID | AC146: Particular | AD146: 12211430-V | AE146: =+VLOOKUP(H146,'Mapeo Ramos'!A:C,3,0) -> Autos Flotas | AF146: =+VLOOKUP(AE146,'Mapeo Ramos'!C:D,2,0) -> Flotas | AG146: =+VLOOKUP(X146,'Mapeo Ramos'!I:J,2,0) -> ALLIANZ | AH146: =+MONTH(E146) -> 1
A147: 2026000570 | B147: 580626475 | C147: 14193664-02193 | D147: 46024 | E147: 46024 | F147: 46023 | G147: FRANCISCO JAVIER MARTIN ALVAREZ | H147: AUTOGRUP V.03 (VH.COM 1ªCATEG.) | I147: AUTO FLOTA | J147: 3105.94 | K147: Eur. | L147: 372.71 | M147: Eur. | N147: 372.71 | O147: Eur. | P147: 0 | Q147: Eur. | S147: 0,00 | T147: Eur. | U147: Cartera | V147: Anulado_Cia | W147: BANASEG-SV | X147: ALLIANZ | Y147: AUTOS | Z147: Correduría | AA147: 47013 | AB147: VALLADOLID VALLADOLID | AC147: Particular | AD147: 12380337-N | AE147: =+VLOOKUP(H147,'Mapeo Ramos'!A:C,3,0) -> Autos Flotas | AF147: =+VLOOKUP(AE147,'Mapeo Ramos'!C:D,2,0) -> Flotas | AG147: =+VLOOKUP(X147,'Mapeo Ramos'!I:J,2,0) -> ALLIANZ | AH147: =+MONTH(E147) -> 1
A148: 2026000584 | B148: 580585275 | C148: 12070250-00410 | D148: 46024 | E148: 46024 | F148: 46023 | G148: ECOFLUIDOS S.L. , | H148: ALLIANZ AUTO V. 08 COLECTIVO | I148: AUTO FLOTA | J148: 1420.06 | K148: Eur. | L148: 170.41 | M148: Eur. | N148: 170.41 | O148: Eur. | P148: 0 | Q148: Eur. | S148: 0,00 | T148: Eur. | U148: Cartera | V148: Anulado_Cia | W148: BANASEG-SV | X148: ALLIANZ | Y148: AUTOS | Z148: Correduría | AA148: 47014 | AB148: VALLADOLID VALLADOLID | AC148: Empresa | AD148: B-47332069 | AE148: =+VLOOKUP(H148,'Mapeo Ramos'!A:C,3,0) -> Autos Flotas | AF148: =+VLOOKUP(AE148,'Mapeo Ramos'!C:D,2,0) -> Flotas | AG148: =+VLOOKUP(X148,'Mapeo Ramos'!I:J,2,0) -> ALLIANZ | AH148: =+MONTH(E148) -> 1
A149: 2026000564 | B149: 581097650 | C149: 36780076-01313 | D149: 46024 | E149: 46024 | F149: 46023 | G149: DENISLAV ASENOV ANGELOV | H149: ALLIANZ AUTO V. 08 COLECTIVO | I149: AUTO FLOTA | J149: 669.47 | K149: Eur. | L149: 80.34 | M149: Eur. | N149: 80.34 | O149: Eur. | P149: 0 | Q149: Eur. | S149: 0,00 | T149: Eur. | U149: Cartera | V149: Anulado_Cia | W149: BANASEG-SV | X149: ALLIANZ | Y149: AUTOS | Z149: Correduría | AA149: 47012 | AB149: VALLADOLID VALLADOLID | AC149: Particular | AD149: X7166108-K | AE149: =+VLOOKUP(H149,'Mapeo Ramos'!A:C,3,0) -> Autos Flotas | AF149: =+VLOOKUP(AE149,'Mapeo Ramos'!C:D,2,0) -> Flotas | AG149: =+VLOOKUP(X149,'Mapeo Ramos'!I:J,2,0) -> ALLIANZ | AH149: =+MONTH(E149) -> 1
A150: 2026000571 | B150: 580585788 | C150: 12070250-01673 | D150: 46024 | E150: 46024 | F150: 46023 | G150: JESUS ANDRES ASTORGA | H150: ALLIANZ AUTO V. 08 COLECTIVO | I150: AUTO FLOTA | J150: 435.85 | K150: Eur. | L150: 52.3 | M150: Eur. | N150: 52.3 | O150: Eur. | P150: 0 | Q150: Eur. | S150: 0,00 | T150: Eur. | U150: Cartera | V150: Anulado_Cia | W150: BANASEG-SV | X150: ALLIANZ | Y150: AUTOS | Z150: Correduría | AA150: 48830 | AB150: SODUPE VIZCAYA | AC150: Particular | AD150: 09668801-S | AE150: =+VLOOKUP(H150,'Mapeo Ramos'!A:C,3,0) -> Autos Flotas | AF150: =+VLOOKUP(AE150,'Mapeo Ramos'!C:D,2,0) -> Flotas | AG150: =+VLOOKUP(X150,'Mapeo Ramos'!I:J,2,0) -> ALLIANZ | AH150: =+MONTH(E150) -> 1
A151: 2026000563 | B151: 580585804 | C151: 12070250-01693 | D151: 46024 | E151: 46024 | F151: 46023 | G151: CARLOS DELGADO E HIJOS, S.L. | H151: ALLIANZ AUTO V. 08 COLECTIVO | I151: AUTO FLOTA | J151: 669.72 | K151: Eur. | L151: 80.37 | M151: Eur. | N151: 80.37 | O151: Eur. | P151: 0 | Q151: Eur. | S151: 0,00 | T151: Eur. | U151: Cartera | V151: Anulado_Cia | W151: BANASEG-SV | X151: ALLIANZ | Y151: AUTOS | Z151: Correduría | AA151: 47130 | AB151: SIMANCAS VALLADOLID | AC151: Empresa | AD151: B-47738190 | AE151: =+VLOOKUP(H151,'Mapeo Ramos'!A:C,3,0) -> Autos Flotas | AF151: =+VLOOKUP(AE151,'Mapeo Ramos'!C:D,2,0) -> Flotas | AG151: =+VLOOKUP(X151,'Mapeo Ramos'!I:J,2,0) -> ALLIANZ | AH151: =+MONTH(E151) -> 1
A152: 2026000577 | B152: 580588246 | C152: 12372022-00665 | D152: 46024 | E152: 46024 | F152: 46023 | G152: JOSE MARIA DEL CAÑO MONEDERO | H152: AUTOGRUP V.03 (VH.COM. 2ª CATEG.) | I152: AUTO FLOTA | J152: 400.86 | K152: Eur. | L152: 48.1 | M152: Eur. | N152: 48.1 | O152: Eur. | P152: 0 | Q152: Eur. | S152: 0,00 | T152: Eur. | U152: Cartera | V152: Anulado_Cia | W152: BANASEG-SV | X152: ALLIANZ | Y152: AUTOS | Z152: Correduría | AA152: 40219 | AB152: VILLAVERDE DE ISCAR SEGOVIA | AC152: Particular | AD152: 03452175-J | AE152: =+VLOOKUP(H152,'Mapeo Ramos'!A:C,3,0) -> Autos Flotas | AF152: =+VLOOKUP(AE152,'Mapeo Ramos'!C:D,2,0) -> Flotas | AG152: =+VLOOKUP(X152,'Mapeo Ramos'!I:J,2,0) -> ALLIANZ | AH152: =+MONTH(E152) -> 1
A153: 2026000575 | B153: 580588568 | C153: 12372022-01256 | D153: 46024 | E153: 46024 | F153: 46023 | G153: JOSE MANUEL FERNANDEZ COTARELO | H153: AUTOGRUP V.03 (VH.COM. 2ª CATEG.) | I153: AUTO FLOTA | J153: 400.86 | K153: Eur. | L153: 48.1 | M153: Eur. | N153: 48.1 | O153: Eur. | P153: 0 | Q153: Eur. | R153: ASETRA | S153: 10.02 | T153: Eur. | U153: Cartera | V153: Anulado_Cia | W153: BANASEG-SV | X153: ALLIANZ | Y153: AUTOS | Z153: Correduría | AA153: 47140 | AB153: LAGUNA DE DUERO VALLADOLID | AC153: Particular | AD153: 71602294-M | AE153: =+VLOOKUP(H153,'Mapeo Ramos'!A:C,3,0) -> Autos Flotas | AF153: =+VLOOKUP(AE153,'Mapeo Ramos'!C:D,2,0) -> Flotas | AG153: =+VLOOKUP(X153,'Mapeo Ramos'!I:J,2,0) -> ALLIANZ | AH153: =+MONTH(E153) -> 1
A154: 2026000576 | B154: 580588576 | C154: 12372022-01258 | D154: 46024 | E154: 46024 | F154: 46023 | G154: JOSE MANUEL FERNANDEZ COTARELO | H154: AUTOGRUP V.03 (VH.COM. 2ª CATEG.) | I154: AUTO FLOTA | J154: 1259.09 | K154: Eur. | L154: 151.09 | M154: Eur. | N154: 151.09 | O154: Eur. | P154: 0 | Q154: Eur. | R154: ASETRA | S154: 31.48 | T154: Eur. | U154: Cartera | V154: Anulado_Cia | W154: BANASEG-SV | X154: ALLIANZ | Y154: AUTOS | Z154: Correduría | AA154: 47140 | AB154: LAGUNA DE DUERO VALLADOLID | AC154: Particular | AD154: 71602294-M | AE154: =+VLOOKUP(H154,'Mapeo Ramos'!A:C,3,0) -> Autos Flotas | AF154: =+VLOOKUP(AE154,'Mapeo Ramos'!C:D,2,0) -> Flotas | AG154: =+VLOOKUP(X154,'Mapeo Ramos'!I:J,2,0) -> ALLIANZ | AH154: =+MONTH(E154) -> 1
A155: 2026000567 | B155: 580625204 | C155: 14193664-01847 | D155: 46024 | E155: 46024 | F155: 46023 | G155: FERNANDO SANCHEZ VELASCO | H155: AUTOGRUP V.03 (VH.COM 1ªCATEG.) | I155: AUTO FLOTA | J155: 1842.67 | K155: Eur. | L155: 221.12 | M155: Eur. | N155: 221.12 | O155: Eur. | P155: 0 | Q155: Eur. | S155: 0,00 | T155: Eur. | U155: Cartera | V155: Anulado_Cia | W155: BANASEG-SV | X155: ALLIANZ | Y155: AUTOS | Z155: Correduría | AA155: 47130 | AB155: SIMANCAS VALLADOLID | AC155: Particular | AD155: 12233975-E | AE155: =+VLOOKUP(H155,'Mapeo Ramos'!A:C,3,0) -> Autos Flotas | AF155: =+VLOOKUP(AE155,'Mapeo Ramos'!C:D,2,0) -> Flotas | AG155: =+VLOOKUP(X155,'Mapeo Ramos'!I:J,2,0) -> ALLIANZ | AH155: =+MONTH(E155) -> 1
A156: 2026000572 | B156: 580625782 | C156: 14193664-02082 | D156: 46024 | E156: 46024 | F156: 46023 | G156: JESUS MERINO DIEZ | H156: AUTOGRUP V.03 (VH.COM 1ªCATEG.) | I156: AUTO FLOTA | J156: 2271.06 | K156: Eur. | L156: 272.53 | M156: Eur. | N156: 272.53 | O156: Eur. | P156: 0 | Q156: Eur. | S156: 0,00 | T156: Eur. | U156: Cartera | V156: Anulado_Cia | W156: BANASEG-SV | X156: ALLIANZ | Y156: AUTOS | Z156: Correduría | AA156: 47270 | AB156: CIGALES VALLADOLID | AC156: Particular | AD156: 71023013-W | AE156: =+VLOOKUP(H156,'Mapeo Ramos'!A:C,3,0) -> Autos Flotas | AF156: =+VLOOKUP(AE156,'Mapeo Ramos'!C:D,2,0) -> Flotas | AG156: =+VLOOKUP(X156,'Mapeo Ramos'!I:J,2,0) -> ALLIANZ | AH156: =+MONTH(E156) -> 1
A157: 2026000558 | B157: 580626020 | C157: 14193664-02122 | D157: 46024 | E157: 46024 | F157: 46023 | G157: ANDERSON DAVID ROBLES TORRES | H157: AUTOGRUP V.03 (VH.COM 1ªCATEG.) | I157: AUTO FLOTA | J157: 3943.86 | K157: Eur. | L157: 473.26 | M157: Eur. | N157: 473.26 | O157: Eur. | P157: 0 | Q157: Eur. | S157: 0,00 | T157: Eur. | U157: Cartera | V157: Anulado_Cia | W157: BANASEG-SV | X157: ALLIANZ | Y157: AUTOS | Z157: Correduría | AA157: 47013 | AB157: VALLADOLID VALLADOLID | AC157: Particular | AD157: 12434426-M | AE157: =+VLOOKUP(H157,'Mapeo Ramos'!A:C,3,0) -> Autos Flotas | AF157: =+VLOOKUP(AE157,'Mapeo Ramos'!C:D,2,0) -> Flotas | AG157: =+VLOOKUP(X157,'Mapeo Ramos'!I:J,2,0) -> ALLIANZ | AH157: =+MONTH(E157) -> 1
A158: 2026000580 | B158: 580626202 | C158: 14193664-02145 | D158: 46024 | E158: 46024 | F158: 46023 | G158: JUAN ANTONIO BECERRA RICO | H158: AUTOGRUP V.03 (VH.COM 1ªCATEG.) | I158: AUTO FLOTA | J158: 2274.41 | K158: Eur. | L158: 272.93 | M158: Eur. | N158: 272.93 | O158: Eur. | P158: 0 | Q158: Eur. | S158: 0,00 | T158: Eur. | U158: Cartera | V158: Anulado_Cia | W158: BANASEG-SV | X158: ALLIANZ | Y158: AUTOS | Z158: Correduría | AA158: 47195 | AB158: ARROYO DE LA ENCOMIENDA VALLADOLID | AC158: Particular | AD158: 71136697-C | AE158: =+VLOOKUP(H158,'Mapeo Ramos'!A:C,3,0) -> Autos Flotas | AF158: =+VLOOKUP(AE158,'Mapeo Ramos'!C:D,2,0) -> Flotas | AG158: =+VLOOKUP(X158,'Mapeo Ramos'!I:J,2,0) -> ALLIANZ | AH158: =+MONTH(E158) -> 1
A159: 2026000566 | B159: 580626590 | C159: 14193664-02208 | D159: 46024 | E159: 46024 | F159: 46023 | G159: ELVIA MARIA PEREZ COMPRES | H159: AUTOGRUP V.03 (VH.COM 1ªCATEG.) | I159: AUTO FLOTA | J159: 1225.17 | K159: Eur. | L159: 147.02 | M159: Eur. | N159: 147.02 | O159: Eur. | P159: 0 | Q159: Eur. | S159: 0,00 | T159: Eur. | U159: Cartera | V159: Anulado_Cia | W159: BANASEG-SV | X159: ALLIANZ | Y159: AUTOS | Z159: Correduría | AA159: 47195 | AB159: ARROYO DE LA ENCOMIENDA VALLADOLID | AC159: Particular | AD159: 71205794-W | AE159: =+VLOOKUP(H159,'Mapeo Ramos'!A:C,3,0) -> Autos Flotas | AF159: =+VLOOKUP(AE159,'Mapeo Ramos'!C:D,2,0) -> Flotas | AG159: =+VLOOKUP(X159,'Mapeo Ramos'!I:J,2,0) -> ALLIANZ | AH159: =+MONTH(E159) -> 1
...

Sheet Mapeo Ramos
A1: Producto | B1: Ramo | C1: Equivalencia 08/2025 | D1: Equivalencia
A2: 1216-ALLIANZ PATINETE | B2: AUTOS | C2: Autos Cat. 3 | D2: Autos | I2: MAPFRE ESPAÑA, S.A. | J2: MAPFRE
A3: 43 - ARAG NEGOCIO FLEXIBLE | B3: P.JURIDICA | C3: Defensa Jurídica | D3: Particulares Resto | I3: ALLIANZ | J3: ALLIANZ
A4: ACC. BAJA DIARIA | C4: Accidentes Convenio | D4: Seguros Personales (No Vida) Colectivos | I4: OCCIDENT GCO, S.A.U. DE SEGUROS Y REASEGUROS | J4: OCCIDENT
A5: ACC. COLECTIVO | B5: ACCIDENTES | C5: Accidentes Colectivo | D5: Seguros Personales (No Vida) Colectivos | I5: ESPABROK | J5: ESPABROK
A6: ACC. COLECTIVO GR | C6: Accidentes Colectivo | D6: Seguros Personales (No Vida) Colectivos | I6: MARKEL INSURANCE SE | J6: MARKEL
A7: ACC. COLECTIVOS EMPRESAS | C7: Accidentes Colectivo | D7: Seguros Personales (No Vida) Colectivos | I7: ARAG S.E. | J7: ARAG
A8: ACC. CONVENIO | B8: ACCIDENTES | C8: Accidentes Convenio | D8: Seguros Personales (No Vida) Colectivos | I8: AXA SEG.GNRALES | J8: AXA
A9: ACC. CONVENIO G.R | B9: ACCIDENTES | C9: Accidentes Convenio | D9: Seguros Personales (No Vida) Colectivos | I9: FIATC | J9: FIATC
A10: ACCID. INDIVID. 2006 | C10: Accidentes Individual | D10: Seguros Personales (No Vida) Particular | I10: GENERALI ESPAÑA | J10: GENERALI
A11: ACCIDENTE INDIVIDUAL | B11: ACCIDENTES | C11: Accidentes Individual | D11: Seguros Personales (No Vida) Particular | I11: REALE | J11: REALE
A12: ACCIDENTES | C12: Accidentes Individual | D12: Seguros Personales (No Vida) Particular | I12: HELVETIA | J12: HELVETIA
A13: ACCIDENTES | C13: Accidentes Individual | D13: Seguros Personales (No Vida) Particular | I13: CASER SEGUROS | J13: CASER
A14: ACCIDENTES COLECTIVO | B14: ACCIDENTES | C14: Accidentes Colectivo | D14: Seguros Personales (No Vida) Colectivos | I14: ASEFA | J14: ASEFA
A15: ACCIDENTES COLECTIVOS | B15: ACCIDENTES | C15: Accidentes Colectivo | D15: Seguros Personales (No Vida) Colectivos | I15: AIG EUROPE, S.A. SUCURSAL EN ESPAÑA | J15: AIG
A16: ACCIDENTES CONVENIO | B16: ACCIDENTES | C16: Accidentes Convenio | D16: Seguros Personales (No Vida) Colectivos | I16: SANITAS | J16: SANITAS
A17: ACCIDENTES CONVENIO COLECTIVO | B17: ACCIDENTES | C17: Accidentes Convenio | D17: Seguros Personales (No Vida) Colectivos | I17: ASISA | J17: ASISA
A18: ACCIDENTES CONVENIO PYME | B18: ACCIDENTES | C18: Accidentes Convenio | D18: Seguros Personales (No Vida) Colectivos | I18: ZURICH INSURANCE | J18: ZURICH
A19: ACCIDENTES INDIVIDUAL | B19: ACCIDENTES | C19: Accidentes Individual | D19: Seguros Personales (No Vida) Particular | I19: DKV | J19: DKV
A20: ACCIDENTES INDIVIDUALES | C20: Accidentes Individual | D20: Seguros Personales (No Vida) Particular | I20: ADESLAS | J20: SEGURCAIXA ADESLAS
A21: ACTIVIDADES EMPRESARIALES | B21: M. INDUSTRIAL | C21: Multirriesgo Industriales (PYME) | D21: Property | I21: SURNE | J21: SVRNE
A22: AGRARIA GENERICA - EXPLOTACIONES Y GRANJAS | C22: Multirriesgo Industriales (PYME) | D22: Property | I22: VIDA CAIXA | J22: SEGURCAIXA ADESLAS
A23: AGRICOLA/REMOLQUES/CAMIONES | B23: AUTOS | C23: Autos Cat. 2 | D23: Flotas | I23: MUTUA DE PROPIETARIOS | J23: MUTUA PROPIETARIOS
A24: AGROCASER EXPLOTACIONES AGROPECUARIAS | B24: M. INDUSTRIAL | C24: Otros Multirriesgo | D24: Property | I24: CATALANA-OCCIDENTE | J24: OCCIDENT
A25: AHORRO | C25: Vida Ahorro Individual | D25: Vida Ahorro Particular | I25: SANTA LUCIA VIDA Y PENSIONES, SA | J25: SANTA LUCIA
A26: AHORRO | C26: Vida Ahorro Individual | D26: Vida Ahorro Particular | I26: MUTUA MADRILEÑA AUTOMOVILISTA SSPF | J26: MUTUA MADRILEÑA
A27: AHORRO SEGURO | B27: AHORRO | C27: Vida Ahorro Individual | D27: Vida Ahorro Particular | I27: LIBERTY SEGUROS | J27: GENERALI
A28: ALL AUTO | B28: AUTOS | C28: Autos Cat. 1 | D28: Autos | I28: HDI GERLING | J28: HDI
A29: ALL. COMERCIAL | B29: AUTOS | C29: Autos Cat. 1 | D29: Autos | I29: LA PREVISION MALLORQUINA DE SEGUROS, S.A. | J29: PREVISIÓN MALLORQUINA
A30: ALL.COMUNIDADES | B30: M.COMUNIDADES | C30: Comunidades | D30: Property | I30: SOLUNION | J30: SOLUNION
A31: ALLIAN HOGAR | B31: M.HOGAR | C31: Hogar | D31: Hogar | I31: DAS DEFENSA | J31: ONLYGAL
A32: ALLIANZ ACCIDENTES v05 | B32: ACCIDENTES | C32: Accidentes Individual | D32: Seguros Personales (No Vida) Particular | I32: GENERALI SEGUROS Y REASEGUROS, S.A.U. | J32: GENERALI
A33: ALLIANZ AUTO BASICO v.05 | B33: AUTOS | C33: Autos Cat. 1 | D33: Autos | I33: G. SANCHEZ-VALENCIA | J33: NO IDENTIFICADO
A34: ALLIANZ AUTO DAÑOS v.05 | B34: AUTOS | C34: Autos Cat. 1 | D34: Autos | I34: BRUJULA ASESORES S.L | J34: BRUJULA
A35: ALLIANZ AUTO PLUS | B35: AUTOS | C35: Autos Cat. 1 | D35: Autos | I35: BERKLEY | J35: BERKLEY
A36: ALLIANZ AUTO PLUS TODO RIESGO | B36: AUTOS | C36: Autos Cat. 1 | D36: Autos | I36: HISCOX | J36: HISCOX
A37: ALLIANZ AUTO TERCEROS | B37: AUTOS | C37: Autos Cat. 1 | D37: Autos | I37: MIC INSURANCE | J37: MIC INSURANCE
A38: ALLIANZ AUTO TERCEROS COLECTIVO | B38: AUTOS FLOTA | C38: Autos Flotas | D38: Flotas | I38: MUSSAP | J38: MUSSAP
... A40: ALLIANZ AUTO TODO RIESGO V.08 | B40: AUTOS | C40: Autos Cat. 1 | D40: Autos | I40: GENERALI ESPAÑA de Seguros y Reaseguros, S.A. | J40: GENERALI
A41: ALLIANZ AUTO TODO RIESGO V.08 COLECTIVO | B41: AUTO FLOTA | C41: Autos Flotas | D41: Flotas
A42: ALLIANZ AUTO V. 08 COLECTIVO | B42: AUTO FLOTA | C42: Autos Flotas | D42: Flotas
A43: ALLIANZ AUTO V.03 | B43: AUTOS | C43: Autos Cat. 1 | D43: Autos
A44: ALLIANZ AUTO V.08 | B44: AUTOS | C44: Autos Cat. 1 | D44: Autos
A45: ALLIANZ AUTOPATRONOS | B45: AUTOS | C45: Autos Cat. 1 | D45: Autos
A46: ALLIANZ AUTOS BASICO v.05 COLECTIVO | B46: AUTOS FLOTA | C46: Autos Flotas | D46: Flotas
A47: ALLIANZ AUTOS DAÑOS v.05 COLECTIVO | B47: AUTOS FLOTA | C47: Autos Flotas | D47: Flotas
A48: ALLIANZ BASICO.01 | B48: AUTOS | C48: Autos Cat. 1 | D48: Autos
A49: ALLIANZ CICLOMOTOR V.03 | B49: AUTOS | C49: Autos Cat. 3 | D49: Autos
A50: ALLIANZ CICLOMOTOR V.03 (COL/FL) | B50: AUTO FLOTA | C50: Autos Cat. 3 | D50: Autos
A51: ALLIANZ COMERCIO | B51: M.COMERCIO | C51: Multirriesgo Comercios | D51: Property
A52: ALLIANZ COMERCIO, OFICINA Y TALLER 01 | B52: M.COMERCIO | C52: Multirriesgo Comercios | D52: Property
... A69: APORT. IMPOS. PERIODICA | B69: PLAN PENSIONES | C69: Vida Plan de Pensiones Individual | D69: Vida Ahorro Particular
A70: ARAG ALQUILER VIVIENDA | C70: Impago de alquileres | D70: Inmobiliario
A71: ARAG EXPLOTACIONES AGRICOLAS | B71: P.JURIDICA | C71: Defensa Jurídica | D71: Particulares Resto
A72: ARAG EXPLOTACIONES GANADERAS | B72: P.JURIDICA | C72: Defensa Jurídica | D72: Particulares Resto
A73: ARAG FAMILIA 12 MESES | B73: P.JURIDICA | C73: Defensa Jurídica | D73: Particulares Resto
A74: ARAG TRANSPORTE PLUS | B74: P.JURIDICA | C74: Defensa Jurídica | D74: Particulares Resto
A75: ARAG TRANSPORTE PLUS | B75: P.JURIDICA | C75: Defensa Jurídica | D75: Particulares Resto
A76: ASISTENCIA EN VIAJE | B76: ACCIDENTES | C76: Asistencia Viaje | D76: Particulares Resto
A77: ASISTENCIA VIAJE PERSONA | B77: ACCIDENTES | C77: Asistencia Viaje | D77: Particulares Resto
A78: ASISTENCIA Y DECESOS | C78: Decesos | D78: Seguros Personales (No Vida) Particular
A79: AUTO FLOTA ZURICH | B79: AUTOS FLOTA | C79: Autos Flotas | D79: Flotas
A80: AUTO REALE 2 Y 3 CATEGORIA | B80: AUTOS | C80: Autos Cat. 2 | D80: Flotas
A81: AUTO REALE MOTOS | B81: AUTOS | C81: Autos Cat. 3 | D81: Autos
A82: AUTOCARES | B82: AUTOS | C82: Autos Cat. 2 | D82: Flotas
A83: AUTOGRUP | B83: AUTO FLOTA | C83: Autos Flotas | D83: Flotas
A84: AUTOGRUP V.03 (CICLO.) | B84: AUTO FLOTA | C84: Autos Flotas | D84: Flotas
A85: AUTOGRUP V.03 (VH.COM 1ªCATEG.) | B85: AUTO FLOTA | C85: Autos Flotas | D85: Flotas
A86: AUTOGRUP V.03 (VH.COM. 2ª CATEG.) | B86: AUTO FLOTA | C86: Autos Flotas | D86: Flotas
A87: AUTOGRUP V.03(MOTOS) | B87: AUTO FLOTA | C87: Autos Flotas | D87: Flotas
A88: AUTOGRUP V.03(TURISMOS) | B88: AUTO FLOTA | C88: Autos Flotas | D88: Flotas
A89: AUTOMOVILES | B89: AUTOS | C89: Autos Cat. 1 | D89: Autos
A90: AUTOS | B90: AUTOS | C90: Autos Cat. 1 | D90: Autos
... A107: BAJA DIARIA POR ENFERMEDAD | B107: ACCIDENTES | C107: Subsidio | D107: Seguros Personales (No Vida) Particular
A108: CABALLOS | C108: REsponsabilidad Civil Particular | D108: Responsabilidad Civil
A109: CAMION | B109: AUTOS | C109: Autos Cat. 2 | D109: Flotas
A110: CAMIONES | B110: AUTOS | C110: Autos Cat. 2 | D110: Flotas
A111: CAMIONES CAB.TRAC. Y SEMIRE | B111: AUTO FLOTA | C111: Autos Flotas | D111: Flotas
A112: CAP M.N.A. | B112: P.JURIDICA | C112: Defensa Jurídica | D112: Particulares Resto
A113: CASER AUTOS 1ª Y 3ª CATEGORIA | B113: AUTOS | C113: Autos Cat. 1 | D113: Autos
A114: CASER AUTOS 2008 | B114: AUTOS | C114: Autos Cat. 1 | D114: Autos
A115: CASER PYME BODEGAS | B115: M. INDUSTRIAL | C115: Multirriesgo Comercios | D115: Property
A116: CASER PYME ENERGIA | B116: M. INDUSTRIAL | C116: Multirriesgo Industriales (PYME) | D116: Property
A117: CIBERRIESGOS | B117: CIBERRIESGOS | C117: Ciberriesgos | D117: Líneas Financieras
A118: COLECTIVO RIESGO RENOVABLE | B118: VIDA | C118: Vida Riesgo Colectivo | D118: Vida Riesgo Colectivo
A119: COLECTIVO SERVICION COMPLETOS | B119: VIDA | C119: Vida Riesgo Colectivo | D119: Vida Riesgo Colectivo
A120: COMERCIO | B120: M.COMERCIO | C120: Multirriesgo Comercios | D120: Property
... A122: COMERCIOS Y OFICINAS | B122: M.COMERCIO | C122: Multirriesgo Comercios | D122: Property
A123: COMUNIDAD | C123: Multrriesgo Comunidades | D123: Property
A124: CONSTRUCCION | B124: CONSTRUCCIONES | C124: Decenal | D124: Ingeniería
A125: CREDITO | B125: SEGURO DE CREDITO | C125: Crédito | D125: Crédito
A126: CuentaCre | B126: CREDITO | C126: Crédito | D126: Crédito
A127: D&O | B127: D&O | C127: Responsabilidad Civil D&O | D127: Líneas Financieras
A128: D&O HISCOX | C128: Responsabilidad Civil D&O | D128: Líneas Financieras
A129: D&O HISCOX | C129: Responsabilidad Civil D&O | D129: Líneas Financieras
A130: DAÑOS DECENAL | B130: CONSTRUCCIONES | C130: Decenal | D130: Ingeniería
A131: DAS CONDUCCION | B131: P.JURIDICA | C131: Defensa Jurídica | D131: Particulares Resto
A132: DAS DEFENSA JURIDICA CORREDOR DE SEGUROS | B132: P.JURIDICA | C132: Defensa Jurídica | D132: Particulares Resto
A133: DEFENSA JURIDICA FAMILIAR | B133: P.JURIDICA | C133: Defensa Jurídica | D133: Particulares Resto
A134: DEFENSA JURIDICA INFRAC. ADMINIST. TRAFICO | B134: P.JURIDICA | C134: Defensa Jurídica | D134: Particulares Resto
...
